Projetos/Modulo LCD DE2 Cyclone II/LCD.v
module LCD (data, selectCD, clk, rst, LCD_DATA, LCD_RW, LCD_RS, LCD_ON, LCD_BLON, enableWriting, LCD_Available);

    input wire [31:0] data;
    input wire selectCD;
    input wire enableWriting;
    input wire clk;
    input wire rst;

    output wire [7:0] LCD_DATA;
    output wire LCD_RW;
    output wire LCD_RS;
    output wire LCD_ON;
    output wire LCD_BLON;
    output wire LCD_Available;


    reg select_ReadOrWrite;
    reg enableNext;
    reg select_CommandOrData;
    reg powerON;
    reg backlightON;
    reg actualLine;
    reg LCDAvailable;
    reg [31:0] localData;

    //Pin assignments

    assign LCD_DATA = currCmd;
    assign LCD_RW = select_ReadOrWrite;
    assign LCD_RS = select_CommandOrData;
    assign LCD_ON = powerON;
    assign LCD_BLON = backlightON;
    assign LCD_Available = LCDAvailable;


    //For the FSA ---------------------------------------------------------------------

    reg [3:0] currState;
    reg [7:0] delayClocks;
    reg [7:0] currCmd;
    reg [3:0] nextState;

    parameter initState1 = 4'd0;
    parameter initStateCommand = 4'd1;
    parameter initState2 = 4'd2;
    parameter byte0 = 4'd4;
    parameter byte1 = 4'd5;
    parameter byte2 = 4'd6;
    parameter byte3 = 4'd7;
    parameter waitingState = 4'd8;
    parameter PULSE_HIGH = 4'd14;
    parameter resetState = 4'd15;

    

    always @(posedge clk or posedge rst) begin
        if (rst) begin
            currState <= resetState;
            enableNext <= 1'b0;
        end

        else begin
            case (currState)
                initState1: begin
                    enableNext <= 1'b0;
                    currCmd <= 8'h0C;
                    select_CommandOrData <= 1'b0;


                    localData <= 32'b0;

                    currState <= PULSE_HIGH;
                    nextState <= waitingState;
                    LCDAvailable <= 1'b0;

                end

                initState2: begin
                    enableNext <= 1'b0;
                    currCmd <= 8'h00;
                    localData <= data;
                    currState <= PULSE_HIGH;
                    nextState <= (selectCD) ? byte0 : initStateCommand;
                    LCDAvailable <= 1'b0;


                end

                byte0: begin
                    enableNext <= 1'b0;
                    select_CommandOrData <= 1'b1;
                    if (localData[31:24] == "\n") begin
                        actualLine <= ~actualLine;
                        currCmd <= 8'h00;
                    end
                    else begin
                        currCmd <= localData[31:24];

                    end
                    
                    currState <= PULSE_HIGH;
                    nextState <= byte1;

                end
                byte1: begin
                    enableNext <= 1'b0;
                    select_CommandOrData <= 1'b1;
                    if (localData[23:16] == "\n") begin
                        actualLine <= ~actualLine;
                        currCmd <= 8'h00;
                    end
                    else begin
                        currCmd <= localData[23:16];

                    end
                    
                    currState <= PULSE_HIGH;
                    nextState <= byte2;

                end
                byte2: begin
                    enableNext <= 1'b0;
                    select_CommandOrData <= 1'b1;
                    if (localData[15:8] == "\n") begin
                        actualLine <= ~actualLine;
                        currCmd <= 8'h00;
                    end
                    else begin
                        currCmd <= localData[15:8];

                    end
                    
                    currState <= PULSE_HIGH;
                    nextState <= byte3;

                end
                byte3: begin
                    enableNext <= 1'b0;
                    select_CommandOrData <= 1'b1;
                    if (localData[7:0] == "\n") begin
                        actualLine <= ~actualLine;
                        currCmd <= 8'h00;
                    end
                    else begin
                        currCmd <= localData[7:0];

                    end
                    
                    currState <= PULSE_HIGH;
                    nextState <= waitingState;

                end

                waitingState: begin
                    enableNext <= 1'b0;
                    currCmd <= 8'h00;
                    select_CommandOrData <= 1'b0;
                    currState <= (enableWriting) ? initState2 : waitingState;
                    LCDAvailable <= 1'b1;
                end

                resetState: begin
                    select_ReadOrWrite <= 1'b0;
                    select_CommandOrData <= 1'b0;
                    powerON <= 1'b1;
                    delayClocks <= 8'b0;
                    backlightON <= 1'b1;
                    currCmd <= 8'h38;
                    LCDAvailable <= 1'b0;

                    currState <= PULSE_HIGH;
                    nextState <= initState1;
                    enableNext <= 1'b0;
                    
                end

                PULSE_HIGH: begin
                    
                    enableNext <= 1'b1;
                    currState <= nextState;


                end

                default: begin
                    
                    currState <= resetState;

                end
            endcase

        end
    end

    //--------------------------------------------------------


endmodule

Projetos/Modulo LCD DE2 Cyclone II/LCD_test.v
module LCD_test;

    reg [31:0] data;
    reg selectCD;
    reg enableWriting;
    reg clk;
    reg rst;

    wire [7:0] LCD_DATA;
    wire LCD_RW;
    wire LCD_RS;
    wire LCD_ON;
    wire LCD_BLON;
    wire LCDAvailable;

    LCD lcd (
        .data(data),
        .selectCD(selectCD),
        .clk(clk),
        .rst(rst),
        .LCD_DATA(LCD_DATA),
        .LCD_RW(LCD_RW),
        .LCD_RS(LCD_RS),
        .LCD_ON(LCD_ON),
        .LCD_BLON(LCD_BLON),
        .enableWriting(enableWriting),
        .LCD_Available(LCDAvailable)
    );

    

    initial begin

        $dumpfile("LCD_test.vcd");
        $dumpvars(0, LCD_test);
        // Initialize signals
        clk = 0;
        rst = 1;
        selectCD = 1;
        enableWriting = 0;
        data = 32'b0;

        // Reset the LCD
        #10 rst = 0;

        wait (LCDAvailable);

        // Write "HELLO WILL!" to the LCD
        #10 data = "HELL";
        enableWriting = 1;
        #10 enableWriting = 0;
        wait (LCDAvailable);

        #10 data = "O WI";
        enableWriting = 1;
        #10 enableWriting = 0;
        wait (LCDAvailable);

        #10 data = "LL!";
        enableWriting = 1;
        #10 enableWriting = 0;
        wait (LCDAvailable);

        #300 $finish;
    end

    initial begin
        #10;
        forever begin
            #5 clk = ~clk;
        end
    end

endmodule

Projetos/Modulo LCD DE2 Cyclone II/LCD_test.vcd
$date
	Sat Mar 15 01:31:38 2025
$end
$version
	Icarus Verilog
$end
$timescale
	1s
$end
$scope module LCD_test $end
$var wire 1 ! LCD_RW $end
$var wire 1 " LCD_RS $end
$var wire 1 # LCD_ON $end
$var wire 8 $ LCD_DATA [7:0] $end
$var wire 1 % LCD_BLON $end
$var wire 1 & LCDAvailable $end
$var reg 1 ' clk $end
$var reg 32 ( data [31:0] $end
$var reg 1 ) enableWriting $end
$var reg 1 * rst $end
$var reg 1 + selectCD $end
$scope module lcd $end
$var wire 1 & LCD_Available $end
$var wire 1 % LCD_BLON $end
$var wire 8 , LCD_DATA [7:0] $end
$var wire 1 # LCD_ON $end
$var wire 1 " LCD_RS $end
$var wire 1 ! LCD_RW $end
$var wire 1 ' clk $end
$var wire 32 - data [31:0] $end
$var wire 1 ) enableWriting $end
$var wire 1 * rst $end
$var wire 1 + selectCD $end
$var parameter 4 . PULSE_HIGH $end
$var parameter 4 / byte0 $end
$var parameter 4 0 byte1 $end
$var parameter 4 1 byte2 $end
$var parameter 4 2 byte3 $end
$var parameter 4 3 initState1 $end
$var parameter 4 4 initState2 $end
$var parameter 4 5 initStateCommand $end
$var parameter 4 6 resetState $end
$var parameter 4 7 waitingState $end
$var reg 1 8 LCDAvailable $end
$var reg 1 9 actualLine $end
$var reg 1 : backlightON $end
$var reg 8 ; currCmd [7:0] $end
$var reg 4 < currState [3:0] $end
$var reg 8 = delayClocks [7:0] $end
$var reg 1 > enableNext $end
$var reg 32 ? localData [31:0] $end
$var reg 4 @ nextState [3:0] $end
$var reg 1 A powerON $end
$var reg 1 B select_CommandOrData $end
$var reg 1 C select_ReadOrWrite $end
$upscope $end
$upscope $end
$enddefinitions $end
$comment Show the parameter values. $end
$dumpall
b1000 7
b1111 6
b1 5
b10 4
b0 3
b111 2
b110 1
b101 0
b100 /
b1110 .
$end
#0
$dumpvars
xC
xB
xA
bx @
bx ?
0>
bx =
b1111 <
bx ;
x:
x9
x8
b0 -
bx ,
1+
1*
0)
b0 (
0'
x&
x%
bx $
x#
x"
x!
$end
#10
0*
#15
b0 @
b1110 <
0&
08
b111000 $
b111000 ,
b111000 ;
1%
1:
b0 =
1#
1A
0"
0B
0!
0C
1'
#20
0'
#25
b0 <
1>
1'
#30
0'
#35
b1000 @
b1110 <
b0 ?
b1100 $
b1100 ,
b1100 ;
0>
1'
#40
0'
#45
b1000 <
1>
1'
#50
0'
#55
1&
18
b0 $
b0 ,
b0 ;
0>
1'
#60
0'
#65
b10 <
1'
1)
b1001000010001010100110001001100 (
b1001000010001010100110001001100 -
#70
0'
#75
0&
08
b100 @
b1110 <
b1001000010001010100110001001100 ?
1'
0)
#80
0'
#85
b100 <
1>
1'
1)
b1001111001000000101011101001001 (
b1001111001000000101011101001001 -
#90
0'
#95
b101 @
b1110 <
b1001000 $
b1001000 ,
b1001000 ;
1"
1B
0>
1'
0)
#100
0'
#105
b101 <
1>
1'
#110
0'
#115
b110 @
b1110 <
b1000101 $
b1000101 ,
b1000101 ;
0>
1'
#120
0'
#125
b110 <
1>
1'
#130
0'
#135
b111 @
b1110 <
b1001100 $
b1001100 ,
b1001100 ;
0>
1'
#140
0'
#145
b111 <
1>
1'
#150
0'
#155
b1000 @
b1110 <
0>
1'
#160
0'
#165
b1000 <
1>
1'
#170
0'
#175
1&
18
0"
0B
b0 $
b0 ,
b0 ;
0>
1'
#180
0'
#185
b10 <
1'
1)
b10011000100110000100001 (
b10011000100110000100001 -
#190
0'
#195
0&
08
b100 @
b1110 <
b10011000100110000100001 ?
1'
0)
#200
0'
#205
b100 <
1>
1'
#210
0'
#215
b101 @
b1110 <
1"
1B
0>
1'
#220
0'
#225
b101 <
1>
1'
#230
0'
#235
b110 @
b1110 <
b1001100 $
b1001100 ,
b1001100 ;
0>
1'
#240
0'
#245
b110 <
1>
1'
#250
0'
#255
b111 @
b1110 <
0>
1'
#260
0'
#265
b111 <
1>
1'
#270
0'
#275
b1000 @
b1110 <
b100001 $
b100001 ,
b100001 ;
0>
1'
#280
0'
#285
b1000 <
1>
1'
#290
0'
#295
1&
18
0"
0B
b0 $
b0 ,
b0 ;
0>
1'
