Projetos/Modulo LCD DE2 Cyclone II/LCD.v
module LCD (data, selectCD, clk, rst, LCD_DATA, LCD_RW, LCD_RS, LCD_ON, LCD_BLON, LCD_EN, enableWriting, LCD_Available);

    input wire [31:0] data;
    input wire selectCD;
    input wire enableWriting;
    input wire clk;
    input wire rst;

    inout wire [7:0] LCD_DATA;

    output wire LCD_RW;
    output wire LCD_RS;
    output wire LCD_ON;
    output wire LCD_BLON;
    output wire LCD_Available;
    output wire LCD_EN;

    wire LCD_BUSYFLAG;


    reg select_ReadOrWrite;
    reg enableNext;
    reg select_CommandOrData;
    reg powerON;
    reg backlightON;
    reg actualLine;
    reg LCDAvailable;
    reg [31:0] localData;
    reg hasTested;

    //Pin assignments

    assign LCD_DATA = (select_ReadOrWrite == 1'b0) ? currCmd : 8'bz;
    assign LCD_RW = select_ReadOrWrite;
    assign LCD_RS = select_CommandOrData;
    assign LCD_ON = powerON;
    assign LCD_BLON = backlightON;
    assign LCD_Available = LCDAvailable;
    assign LCD_BUSYFLAG = LCD_DATA[7];
    assign LCD_EN = enableNext;


    //For the FSA ---------------------------------------------------------------------

    reg [3:0] currState;
    reg [5:0] delayClocks;
    reg [7:0] currCmd;
    reg [3:0] nextState;

    parameter initState1 = 4'd0;
    parameter initStateCommand = 4'd1;
    parameter initState2 = 4'd2;
    parameter byte0 = 4'd4;
    parameter byte1 = 4'd5;
    parameter byte2 = 4'd6;
    parameter byte3 = 4'd7;
    parameter waitingState = 4'd8;
    parameter idle = 4'd9;
    parameter waitNotBusy = 4'd10;
    parameter PULSE_LOW = 4'd13;
    parameter PULSE_HIGH = 4'd14;
    parameter resetState = 4'd15;
    

    

    always @(posedge clk or posedge rst) begin
        if (rst) begin
            currState <= resetState;
            LCDAvailable <= 1'b0;
            enableNext <= 1'b0;
            hasTested <= 1'b0;
            delayClocks <= 0;
        end

        else begin
            case (currState)
                initState1: begin
                    currCmd <= 8'h0C;
                    select_CommandOrData <= 1'b0;
                    localData <= 32'b0;
                    currState <= PULSE_HIGH;
                    nextState <= waitingState;
                    LCDAvailable <= 1'b0;

                end

                initState2: begin
                    currCmd <= 8'h00;
                    select_CommandOrData <= 1'b0;
                    select_ReadOrWrite <= 1'b0;
                    localData <= data;
                    currState <= PULSE_HIGH;
                    nextState <= (selectCD) ? byte0 : initStateCommand;
                    LCDAvailable <= 1'b0;
                    


                end

                byte0: begin
                    select_ReadOrWrite <= 1'b0;
                    select_CommandOrData <= 1'b1;
                    currCmd <= localData[31:24];
                    
                    currState <= PULSE_HIGH;
                    nextState <= byte1;
                    

                end

                byte1: begin
                    select_ReadOrWrite <= 1'b0;
                    enableNext <= 1'b0;
                    select_CommandOrData <= 1'b1;
                    currCmd <= localData[23:16];
                    
                    currState <= PULSE_HIGH;
                    nextState <= byte2;

                end
                byte2: begin
                    
                    enableNext <= 1'b0;
                    select_CommandOrData <= 1'b1;
                    currCmd <= localData[15:8];
                    
                    currState <= PULSE_HIGH;
                    nextState <= byte3;

                end
                byte3: begin
                    select_ReadOrWrite <= 1'b0;
                    enableNext <= 1'b0;
                    select_CommandOrData <= 1'b1;
                    currCmd <= localData[7:0];
                    
                    currState <= PULSE_HIGH;
                    nextState <= waitingState;
                    

                end

                waitNotBusy: begin

                    if (hasTested) begin
                        hasTested <= 1'b0;
                        if (!LCD_BUSYFLAG) begin
                            currState <= nextState;
                            select_ReadOrWrite <= 1'b0;
                        end
                        else begin
                            currState <= waitNotBusy;
                        end
                    end
                    else begin
                        hasTested <= 1'b1;
                        currState <= PULSE_HIGH;
                        select_CommandOrData <= 1'b0;
                        select_ReadOrWrite <= 1'b1;
                    end

                end

                waitingState: begin
                    currCmd <= 8'h00;
                    LCDAvailable <= 1'b1;
                    select_CommandOrData <= 1'b0;
                    currState <= (enableWriting) ? initState2 : waitingState;
                    LCDAvailable <= 1'b1;
                end

                resetState: begin
                    enableNext <= 1'b0;
                    select_ReadOrWrite <= 1'b0;
                    select_CommandOrData <= 1'b0;
                    powerON <= 1'b1;
                    backlightON <= 1'b1;
                    currCmd <= 8'h38;
                    LCDAvailable <= 1'b0;
                    hasTested <= 1'b0;

                    currState <= PULSE_HIGH;
                    nextState <= initState1;

                end

                PULSE_HIGH: begin
                    
                    enableNext <= 1'b1;
                    if (delayClocks < 20) begin
                        delayClocks <= delayClocks + 1;
                        currState <= PULSE_HIGH;
                    end
                    else begin
                        delayClocks <= 0;
                        currState <= PULSE_LOW;
                    end

                end

                PULSE_LOW: begin
                    
                    enableNext <= 1'b0;
                    if (delayClocks < 22) begin
                        delayClocks <= delayClocks + 1;
                        currState <= PULSE_LOW;
                    end
                    else begin
                        delayClocks <= 0;
                        currState <= waitNotBusy;
                    end

                end

                default: begin
                    
                    currState <= resetState;

                end
            endcase

        end
    end

    //--------------------------------------------------------


endmodule

Projetos/Modulo LCD DE2 Cyclone II/LCD_testbench.v
`timescale 1us / 1ns

module LCD_testbench;

  // Sinais de estímulo
  reg  [31:0] data;
  reg         selectCD;
  reg         enableWriting;
  reg         clk;
  reg         rst;

  reg [7:0] fake_LCD_data;
  reg       fake_driver_enable;
  integer   busy_counter;

  // Usamos "tri0" para LCD_DATA para que, quando não for dirigido pelo módulo,
  // ele tenha valor 0 (busy flag baixo).
  tri0 [7:0] LCD_DATA;  

  wire LCD_RW;
  wire LCD_RS;
  wire LCD_ON;
  wire LCD_BLON;
  wire LCD_Available;
  wire LCD_EN;

  

  // Instanciação do módulo LCD (unidade sob teste)
  LCD uut (
    .data(data),
    .selectCD(selectCD),
    .clk(clk),
    .rst(rst),
    .LCD_DATA(LCD_DATA),
    .LCD_RW(LCD_RW),
    .LCD_RS(LCD_RS),
    .LCD_ON(LCD_ON),
    .LCD_BLON(LCD_BLON),
    .enableWriting(enableWriting),
    .LCD_Available(LCD_Available),
    .LCD_EN(LCD_EN)
  );


   initial begin
    fake_LCD_data = 8'h80;  // Busy flag alto (bit 7 = 1)
    fake_driver_enable = 0;
    busy_counter = 0;
  end

  // Esse bloco monitora LCD_RW e simula a operação interna do LCD.
  always @(posedge clk) begin
    if (LCD_RW == 1'b1) begin
      // Quando o módulo está em modo leitura, habilitamos o driver fake.
      fake_driver_enable <= 1'b1;
      // Inicia um contador para manter busy por, por exemplo, 3 ciclos.
      if (busy_counter < 3)
        busy_counter <= busy_counter + 1;
      else
        fake_LCD_data <= 8'h00;  // Após o atraso, busy flag desativa (bit7 = 0)
    end else begin
      fake_driver_enable <= 1'b0;
      busy_counter <= 0;
      fake_LCD_data <= 8'h80; // Prepara para nova simulação de busy
    end
  end


  // Gerador de clock: período de 10 ns
  initial begin
    clk = 0;
    forever #5 clk = ~clk;
  end

  // Sequência de estímulo
  initial begin
    $dumpfile("LCD_testbench.vcd");
    $dumpvars(0, LCD_testbench);

    // Inicializa sinais
    rst = 1;
    data = 32'b0;
    selectCD = 1;       // Supondo que 1 indica escrita de dados (não comando)
    enableWriting = 0;

    // Mantenha reset por 20 ns
    #20;
    rst = 0;

    // Aguarda até que o módulo indique disponibilidade (LCD_Available alto)
    wait(LCD_Available == 1);

    // Primeira escrita: envia "HELL"
    #10;
    data = "HELL";      // Lembre que o literal é empacotado de MSB para LSB
    enableWriting = 1;
    #10;
    enableWriting = 0;

    // Aguarda a liberação para nova escrita
    wait(LCD_Available == 1);

    // Segunda escrita: envia "O WI"
    #10;
    data = "O WI";
    enableWriting = 1;
    #10;
    enableWriting = 0;

    wait(LCD_Available == 1);

    // Terceira escrita: envia "LL! " (com espaço, se desejar)
    #10;
    data = "LL! ";
    enableWriting = 1;
    #10;
    enableWriting = 0;

    wait(LCD_Available == 1);

    #2000 $finish;
  end

endmodule

Projetos/Modulo LCD DE2 Cyclone II/LCD_testbench.vcd
$date
	Tue Mar 18 21:54:25 2025
$end
$version
	Icarus Verilog
$end
$timescale
	1ns
$end
$scope module LCD_testbench $end
$var wire 8 ! LCD_DATA [7:0] $end
$var wire 1 " LCD_RW $end
$var wire 1 # LCD_RS $end
$var wire 1 $ LCD_ON $end
$var wire 1 % LCD_EN $end
$var wire 1 & LCD_BLON $end
$var wire 1 ' LCD_Available $end
$var reg 1 ( clk $end
$var reg 32 ) data [31:0] $end
$var reg 1 * enableWriting $end
$var reg 8 + fake_LCD_data [7:0] $end
$var reg 1 , fake_driver_enable $end
$var reg 1 - rst $end
$var reg 1 . selectCD $end
$var integer 32 / busy_counter [31:0] $end
$scope module uut $end
$var wire 1 ' LCD_Available $end
$var wire 1 & LCD_BLON $end
$var wire 8 0 LCD_DATA [7:0] $end
$var wire 1 % LCD_EN $end
$var wire 1 $ LCD_ON $end
$var wire 1 # LCD_RS $end
$var wire 1 " LCD_RW $end
$var wire 1 ( clk $end
$var wire 32 1 data [31:0] $end
$var wire 1 * enableWriting $end
$var wire 1 - rst $end
$var wire 1 . selectCD $end
$var wire 1 2 LCD_BUSYFLAG $end
$var parameter 4 3 PULSE_HIGH $end
$var parameter 4 4 PULSE_LOW $end
$var parameter 4 5 byte0 $end
$var parameter 4 6 byte1 $end
$var parameter 4 7 byte2 $end
$var parameter 4 8 byte3 $end
$var parameter 4 9 idle $end
$var parameter 4 : initState1 $end
$var parameter 4 ; initState2 $end
$var parameter 4 < initStateCommand $end
$var parameter 4 = resetState $end
$var parameter 4 > waitNotBusy $end
$var parameter 4 ? waitingState $end
$var reg 1 @ LCDAvailable $end
$var reg 1 A backlightON $end
$var reg 8 B currCmd [7:0] $end
$var reg 4 C currState [3:0] $end
$var reg 6 D delayClocks [5:0] $end
$var reg 1 E enableNext $end
$var reg 1 F hasTested $end
$var reg 32 G localData [31:0] $end
$var reg 4 H nextState [3:0] $end
$var reg 1 I powerON $end
$var reg 1 J select_CommandOrData $end
$var reg 1 K select_ReadOrWrite $end
$upscope $end
$upscope $end
$enddefinitions $end
$comment Show the parameter values. $end
$dumpall
b1000 ?
b1010 >
b1111 =
b1 <
b10 ;
b0 :
b1001 9
b111 8
b110 7
b101 6
b100 5
b1101 4
b1110 3
$end
#0
$dumpvars
xK
xJ
xI
bx H
bx G
0F
0E
b0 D
b1111 C
bx B
xA
0@
x2
b0 1
bx 0
b0 /
1.
1-
0,
b10000000 +
0*
b0 )
0(
0'
x&
0%
x$
x#
x"
bx !
$end
#5000
1(
#10000
0(
#15000
1(
#20000
0(
0-
#25000
02
b111000 !
b111000 0
b0 H
b1110 C
b111000 B
1&
1A
1$
1I
0#
0J
0"
0K
1(
#30000
0(
#35000
b1 D
1%
1E
1(
#40000
0(
#45000
b10 D
1(
#50000
0(
#55000
b11 D
1(
#60000
0(
#65000
b100 D
1(
#70000
0(
#75000
b101 D
1(
#80000
0(
#85000
b110 D
1(
#90000
0(
#95000
b111 D
1(
#100000
0(
#105000
b1000 D
1(
#110000
0(
#115000
b1001 D
1(
#120000
0(
#125000
b1010 D
1(
#130000
0(
#135000
b1011 D
1(
#140000
0(
#145000
b1100 D
1(
#150000
0(
#155000
b1101 D
1(
#160000
0(
#165000
b1110 D
1(
#170000
0(
#175000
b1111 D
1(
#180000
0(
#185000
b10000 D
1(
#190000
0(
#195000
b10001 D
1(
#200000
0(
#205000
b10010 D
1(
#210000
0(
#215000
b10011 D
1(
#220000
0(
#225000
b10100 D
1(
#230000
0(
#235000
b1101 C
b0 D
1(
#240000
0(
#245000
b1 D
0%
0E
1(
#250000
0(
#255000
b10 D
1(
#260000
0(
#265000
b11 D
1(
#270000
0(
#275000
b100 D
1(
#280000
0(
#285000
b101 D
1(
#290000
0(
#295000
b110 D
1(
#300000
0(
#305000
b111 D
1(
#310000
0(
#315000
b1000 D
1(
#320000
0(
#325000
b1001 D
1(
#330000
0(
#335000
b1010 D
1(
#340000
0(
#345000
b1011 D
1(
#350000
0(
#355000
b1100 D
1(
#360000
0(
#365000
b1101 D
1(
#370000
0(
#375000
b1110 D
1(
#380000
0(
#385000
b1111 D
1(
#390000
0(
#395000
b10000 D
1(
#400000
0(
#405000
b10001 D
1(
#410000
0(
#415000
b10010 D
1(
#420000
0(
#425000
b10011 D
1(
#430000
0(
#435000
b10100 D
1(
#440000
0(
#445000
b10101 D
1(
#450000
0(
#455000
b10110 D
1(
#460000
0(
#465000
b1010 C
b0 D
1(
#470000
0(
#475000
b0 !
b0 0
1"
1K
b1110 C
1F
1(
#480000
0(
#485000
b1 D
1%
1E
b1 /
1,
1(
#490000
0(
#495000
b10 D
b10 /
1(
#500000
0(
#505000
b11 D
b11 /
1(
#510000
0(
#515000
b100 D
b0 +
1(
#520000
0(
#525000
b101 D
1(
#530000
0(
#535000
b110 D
1(
#540000
0(
#545000
b111 D
1(
#550000
0(
#555000
b1000 D
1(
#560000
0(
#565000
b1001 D
1(
#570000
0(
#575000
b1010 D
1(
#580000
0(
#585000
b1011 D
1(
#590000
0(
#595000
b1100 D
1(
#600000
0(
#605000
b1101 D
1(
#610000
0(
#615000
b1110 D
1(
#620000
0(
#625000
b1111 D
1(
#630000
0(
#635000
b10000 D
1(
#640000
0(
#645000
b10001 D
1(
#650000
0(
#655000
b10010 D
1(
#660000
0(
#665000
b10011 D
1(
#670000
0(
#675000
b10100 D
1(
#680000
0(
#685000
b1101 C
b0 D
1(
#690000
0(
#695000
b1 D
0%
0E
1(
#700000
0(
#705000
b10 D
1(
#710000
0(
#715000
b11 D
1(
#720000
0(
#725000
b100 D
1(
#730000
0(
#735000
b101 D
1(
#740000
0(
#745000
b110 D
1(
#750000
0(
#755000
b111 D
1(
#760000
0(
#765000
b1000 D
1(
#770000
0(
#775000
b1001 D
1(
#780000
0(
#785000
b1010 D
1(
#790000
0(
#795000
b1011 D
1(
#800000
0(
#805000
b1100 D
1(
#810000
0(
#815000
b1101 D
1(
#820000
0(
#825000
b1110 D
1(
#830000
0(
#835000
b1111 D
1(
#840000
0(
#845000
b10000 D
1(
#850000
0(
#855000
b10001 D
1(
#860000
0(
#865000
b10010 D
1(
#870000
0(
#875000
b10011 D
1(
#880000
0(
#885000
b10100 D
1(
#890000
0(
#895000
b10101 D
1(
#900000
0(
#905000
b10110 D
1(
#910000
0(
#915000
b1010 C
b0 D
1(
#920000
0(
#925000
b111000 !
b111000 0
0"
0K
b0 C
0F
1(
#930000
0(
#935000
b1100 !
b1100 0
b1000 H
b1110 C
b0 G
b1100 B
b10000000 +
b0 /
0,
1(
#940000
0(
#945000
b1 D
1%
1E
1(
#950000
0(
#955000
b10 D
1(
#960000
0(
#965000
b11 D
1(
#970000
0(
#975000
b100 D
1(
#980000
0(
#985000
b101 D
1(
#990000
0(
#995000
b110 D
1(
#1000000
0(
#1005000
b111 D
1(
#1010000
0(
#1015000
b1000 D
1(
#1020000
0(
#1025000
b1001 D
1(
#1030000
0(
#1035000
b1010 D
1(
#1040000
0(
#1045000
b1011 D
1(
#1050000
0(
#1055000
b1100 D
1(
#1060000
0(
#1065000
b1101 D
1(
#1070000
0(
#1075000
b1110 D
1(
#1080000
0(
#1085000
b1111 D
1(
#1090000
0(
#1095000
b10000 D
1(
#1100000
0(
#1105000
b10001 D
1(
#1110000
0(
#1115000
b10010 D
1(
#1120000
0(
#1125000
b10011 D
1(
#1130000
0(
#1135000
b10100 D
1(
#1140000
0(
#1145000
b1101 C
b0 D
1(
#1150000
0(
#1155000
b1 D
0%
0E
1(
#1160000
0(
#1165000
b10 D
1(
#1170000
0(
#1175000
b11 D
1(
#1180000
0(
#1185000
b100 D
1(
#1190000
0(
#1195000
b101 D
1(
#1200000
0(
#1205000
b110 D
1(
#1210000
0(
#1215000
b111 D
1(
#1220000
0(
#1225000
b1000 D
1(
#1230000
0(
#1235000
b1001 D
1(
#1240000
0(
#1245000
b1010 D
1(
#1250000
0(
#1255000
b1011 D
1(
#1260000
0(
#1265000
b1100 D
1(
#1270000
0(
#1275000
b1101 D
1(
#1280000
0(
#1285000
b1110 D
1(
#1290000
0(
#1295000
b1111 D
1(
#1300000
0(
#1305000
b10000 D
1(
#1310000
0(
#1315000
b10001 D
1(
#1320000
0(
#1325000
b10010 D
1(
#1330000
0(
#1335000
b10011 D
1(
#1340000
0(
#1345000
b10100 D
1(
#1350000
0(
#1355000
b10101 D
1(
#1360000
0(
#1365000
b10110 D
1(
#1370000
0(
#1375000
b1010 C
b0 D
1(
#1380000
0(
#1385000
b0 !
b0 0
1"
1K
b1110 C
1F
1(
#1390000
0(
#1395000
b1 D
1%
1E
b1 /
1,
1(
#1400000
0(
#1405000
b10 D
b10 /
1(
#1410000
0(
#1415000
b11 D
b11 /
1(
#1420000
0(
#1425000
b100 D
b0 +
1(
#1430000
0(
#1435000
b101 D
1(
#1440000
0(
#1445000
b110 D
1(
#1450000
0(
#1455000
b111 D
1(
#1460000
0(
#1465000
b1000 D
1(
#1470000
0(
#1475000
b1001 D
1(
#1480000
0(
#1485000
b1010 D
1(
#1490000
0(
#1495000
b1011 D
1(
#1500000
0(
#1505000
b1100 D
1(
#1510000
0(
#1515000
b1101 D
1(
#1520000
0(
#1525000
b1110 D
1(
#1530000
0(
#1535000
b1111 D
1(
#1540000
0(
#1545000
b10000 D
1(
#1550000
0(
#1555000
b10001 D
1(
#1560000
0(
#1565000
b10010 D
1(
#1570000
0(
#1575000
b10011 D
1(
#1580000
0(
#1585000
b10100 D
1(
#1590000
0(
#1595000
b1101 C
b0 D
1(
#1600000
0(
#1605000
b1 D
0%
0E
1(
#1610000
0(
#1615000
b10 D
1(
#1620000
0(
#1625000
b11 D
1(
#1630000
0(
#1635000
b100 D
1(
#1640000
0(
#1645000
b101 D
1(
#1650000
0(
#1655000
b110 D
1(
#1660000
0(
#1665000
b111 D
1(
#1670000
0(
#1675000
b1000 D
1(
#1680000
0(
#1685000
b1001 D
1(
#1690000
0(
#1695000
b1010 D
1(
#1700000
0(
#1705000
b1011 D
1(
#1710000
0(
#1715000
b1100 D
1(
#1720000
0(
#1725000
b1101 D
1(
#1730000
0(
#1735000
b1110 D
1(
#1740000
0(
#1745000
b1111 D
1(
#1750000
0(
#1755000
b10000 D
1(
#1760000
0(
#1765000
b10001 D
1(
#1770000
0(
#1775000
b10010 D
1(
#1780000
0(
#1785000
b10011 D
1(
#1790000
0(
#1795000
b10100 D
1(
#1800000
0(
#1805000
b10101 D
1(
#1810000
0(
#1815000
b10110 D
1(
#1820000
0(
#1825000
b1010 C
b0 D
1(
#1830000
0(
#1835000
b1100 !
b1100 0
0"
0K
b1000 C
0F
1(
#1840000
0(
#1845000
b0 !
b0 0
1'
1@
b0 B
b10000000 +
b0 /
0,
1(
#1850000
0(
#1855000
b10 C
1(
1*
b1001000010001010100110001001100 )
b1001000010001010100110001001100 1
#1860000
0(
#1865000
0'
0@
b100 H
b1110 C
b1001000010001010100110001001100 G
1(
0*
#1870000
0(
#1875000
b1 D
1%
1E
1(
1*
b1001111001000000101011101001001 )
b1001111001000000101011101001001 1
#1880000
0(
#1885000
b10 D
1(
0*
#1890000
0(
#1895000
b11 D
1(
#1900000
0(
#1905000
b100 D
1(
#1910000
0(
#1915000
b101 D
1(
#1920000
0(
#1925000
b110 D
1(
#1930000
0(
#1935000
b111 D
1(
#1940000
0(
#1945000
b1000 D
1(
#1950000
0(
#1955000
b1001 D
1(
#1960000
0(
#1965000
b1010 D
1(
#1970000
0(
#1975000
b1011 D
1(
#1980000
0(
#1985000
b1100 D
1(
#1990000
0(
#1995000
b1101 D
1(
#2000000
0(
#2005000
b1110 D
1(
#2010000
0(
#2015000
b1111 D
1(
#2020000
0(
#2025000
b10000 D
1(
#2030000
0(
#2035000
b10001 D
1(
#2040000
0(
#2045000
b10010 D
1(
#2050000
0(
#2055000
b10011 D
1(
#2060000
0(
#2065000
b10100 D
1(
#2070000
0(
#2075000
b1101 C
b0 D
1(
#2080000
0(
#2085000
b1 D
0%
0E
1(
#2090000
0(
#2095000
b10 D
1(
#2100000
0(
#2105000
b11 D
1(
#2110000
0(
#2115000
b100 D
1(
#2120000
0(
#2125000
b101 D
1(
#2130000
0(
#2135000
b110 D
1(
#2140000
0(
#2145000
b111 D
1(
#2150000
0(
#2155000
b1000 D
1(
#2160000
0(
#2165000
b1001 D
1(
#2170000
0(
#2175000
b1010 D
1(
#2180000
0(
#2185000
b1011 D
1(
#2190000
0(
#2195000
b1100 D
1(
#2200000
0(
#2205000
b1101 D
1(
#2210000
0(
#2215000
b1110 D
1(
#2220000
0(
#2225000
b1111 D
1(
#2230000
0(
#2235000
b10000 D
1(
#2240000
0(
#2245000
b10001 D
1(
#2250000
0(
#2255000
b10010 D
1(
#2260000
0(
#2265000
b10011 D
1(
#2270000
0(
#2275000
b10100 D
1(
#2280000
0(
#2285000
b10101 D
1(
#2290000
0(
#2295000
b10110 D
1(
#2300000
0(
#2305000
b1010 C
b0 D
1(
#2310000
0(
#2315000
b0 !
b0 0
1"
1K
b1110 C
1F
1(
#2320000
0(
#2325000
b1 D
1%
1E
b1 /
1,
1(
#2330000
0(
#2335000
b10 D
b10 /
1(
#2340000
0(
#2345000
b11 D
b11 /
1(
#2350000
0(
#2355000
b100 D
b0 +
1(
#2360000
0(
#2365000
b101 D
1(
#2370000
0(
#2375000
b110 D
1(
#2380000
0(
#2385000
b111 D
1(
#2390000
0(
#2395000
b1000 D
1(
#2400000
0(
#2405000
b1001 D
1(
#2410000
0(
#2415000
b1010 D
1(
#2420000
0(
#2425000
b1011 D
1(
#2430000
0(
#2435000
b1100 D
1(
#2440000
0(
#2445000
b1101 D
1(
#2450000
0(
#2455000
b1110 D
1(
#2460000
0(
#2465000
b1111 D
1(
#2470000
0(
#2475000
b10000 D
1(
#2480000
0(
#2485000
b10001 D
1(
#2490000
0(
#2495000
b10010 D
1(
#2500000
0(
#2505000
b10011 D
1(
#2510000
0(
#2515000
b10100 D
1(
#2520000
0(
#2525000
b1101 C
b0 D
1(
#2530000
0(
#2535000
b1 D
0%
0E
1(
#2540000
0(
#2545000
b10 D
1(
#2550000
0(
#2555000
b11 D
1(
#2560000
0(
#2565000
b100 D
1(
#2570000
0(
#2575000
b101 D
1(
#2580000
0(
#2585000
b110 D
1(
#2590000
0(
#2595000
b111 D
1(
#2600000
0(
#2605000
b1000 D
1(
#2610000
0(
#2615000
b1001 D
1(
#2620000
0(
#2625000
b1010 D
1(
#2630000
0(
#2635000
b1011 D
1(
#2640000
0(
#2645000
b1100 D
1(
#2650000
0(
#2655000
b1101 D
1(
#2660000
0(
#2665000
b1110 D
1(
#2670000
0(
#2675000
b1111 D
1(
#2680000
0(
#2685000
b10000 D
1(
#2690000
0(
#2695000
b10001 D
1(
#2700000
0(
#2705000
b10010 D
1(
#2710000
0(
#2715000
b10011 D
1(
#2720000
0(
#2725000
b10100 D
1(
#2730000
0(
#2735000
b10101 D
1(
#2740000
0(
#2745000
b10110 D
1(
#2750000
0(
#2755000
b1010 C
b0 D
1(
#2760000
0(
#2765000
b0 !
b0 0
0"
0K
b100 C
0F
1(
#2770000
0(
#2775000
b1001000 !
b1001000 0
b101 H
b1110 C
b1001000 B
1#
1J
b10000000 +
b0 /
0,
1(
#2780000
0(
#2785000
b1 D
1%
1E
1(
#2790000
0(
#2795000
b10 D
1(
#2800000
0(
#2805000
b11 D
1(
#2810000
0(
#2815000
b100 D
1(
#2820000
0(
#2825000
b101 D
1(
#2830000
0(
#2835000
b110 D
1(
#2840000
0(
#2845000
b111 D
1(
#2850000
0(
#2855000
b1000 D
1(
#2860000
0(
#2865000
b1001 D
1(
#2870000
0(
#2875000
b1010 D
1(
#2880000
0(
#2885000
b1011 D
1(
#2890000
0(
#2895000
b1100 D
1(
#2900000
0(
#2905000
b1101 D
1(
#2910000
0(
#2915000
b1110 D
1(
#2920000
0(
#2925000
b1111 D
1(
#2930000
0(
#2935000
b10000 D
1(
#2940000
0(
#2945000
b10001 D
1(
#2950000
0(
#2955000
b10010 D
1(
#2960000
0(
#2965000
b10011 D
1(
#2970000
0(
#2975000
b10100 D
1(
#2980000
0(
#2985000
b1101 C
b0 D
1(
#2990000
0(
#2995000
b1 D
0%
0E
1(
#3000000
0(
#3005000
b10 D
1(
#3010000
0(
#3015000
b11 D
1(
#3020000
0(
#3025000
b100 D
1(
#3030000
0(
#3035000
b101 D
1(
#3040000
0(
#3045000
b110 D
1(
#3050000
0(
#3055000
b111 D
1(
#3060000
0(
#3065000
b1000 D
1(
#3070000
0(
#3075000
b1001 D
1(
#3080000
0(
#3085000
b1010 D
1(
#3090000
0(
#3095000
b1011 D
1(
#3100000
0(
#3105000
b1100 D
1(
#3110000
0(
#3115000
b1101 D
1(
#3120000
0(
#3125000
b1110 D
1(
#3130000
0(
#3135000
b1111 D
1(
#3140000
0(
#3145000
b10000 D
1(
#3150000
0(
#3155000
b10001 D
1(
#3160000
0(
#3165000
b10010 D
1(
#3170000
0(
#3175000
b10011 D
1(
#3180000
0(
#3185000
b10100 D
1(
#3190000
0(
#3195000
b10101 D
1(
#3200000
0(
#3205000
b10110 D
1(
#3210000
0(
#3215000
b1010 C
b0 D
1(
#3220000
0(
#3225000
b0 !
b0 0
1"
1K
0#
0J
b1110 C
1F
1(
#3230000
0(
#3235000
b1 D
1%
1E
b1 /
1,
1(
#3240000
0(
#3245000
b10 D
b10 /
1(
#3250000
0(
#3255000
b11 D
b11 /
1(
#3260000
0(
#3265000
b100 D
b0 +
1(
#3270000
0(
#3275000
b101 D
1(
#3280000
0(
#3285000
b110 D
1(
#3290000
0(
#3295000
b111 D
1(
#3300000
0(
#3305000
b1000 D
1(
#3310000
0(
#3315000
b1001 D
1(
#3320000
0(
#3325000
b1010 D
1(
#3330000
0(
#3335000
b1011 D
1(
#3340000
0(
#3345000
b1100 D
1(
#3350000
0(
#3355000
b1101 D
1(
#3360000
0(
#3365000
b1110 D
1(
#3370000
0(
#3375000
b1111 D
1(
#3380000
0(
#3385000
b10000 D
1(
#3390000
0(
#3395000
b10001 D
1(
#3400000
0(
#3405000
b10010 D
1(
#3410000
0(
#3415000
b10011 D
1(
#3420000
0(
#3425000
b10100 D
1(
#3430000
0(
#3435000
b1101 C
b0 D
1(
#3440000
0(
#3445000
b1 D
0%
0E
1(
#3450000
0(
#3455000
b10 D
1(
#3460000
0(
#3465000
b11 D
1(
#3470000
0(
#3475000
b100 D
1(
#3480000
0(
#3485000
b101 D
1(
#3490000
0(
#3495000
b110 D
1(
#3500000
0(
#3505000
b111 D
1(
#3510000
0(
#3515000
b1000 D
1(
#3520000
0(
#3525000
b1001 D
1(
#3530000
0(
#3535000
b1010 D
1(
#3540000
0(
#3545000
b1011 D
1(
#3550000
0(
#3555000
b1100 D
1(
#3560000
0(
#3565000
b1101 D
1(
#3570000
0(
#3575000
b1110 D
1(
#3580000
0(
#3585000
b1111 D
1(
#3590000
0(
#3595000
b10000 D
1(
#3600000
0(
#3605000
b10001 D
1(
#3610000
0(
#3615000
b10010 D
1(
#3620000
0(
#3625000
b10011 D
1(
#3630000
0(
#3635000
b10100 D
1(
#3640000
0(
#3645000
b10101 D
1(
#3650000
0(
#3655000
b10110 D
1(
#3660000
0(
#3665000
b1010 C
b0 D
1(
#3670000
0(
#3675000
b1001000 !
b1001000 0
0"
0K
b101 C
0F
1(
#3680000
0(
#3685000
b1000101 !
b1000101 0
b110 H
b1110 C
b1000101 B
1#
1J
b10000000 +
b0 /
0,
1(
#3690000
0(
#3695000
b1 D
1%
1E
1(
#3700000
0(
#3705000
b10 D
1(
#3710000
0(
#3715000
b11 D
1(
#3720000
0(
#3725000
b100 D
1(
#3730000
0(
#3735000
b101 D
1(
#3740000
0(
#3745000
b110 D
1(
#3750000
0(
#3755000
b111 D
1(
#3760000
0(
#3765000
b1000 D
1(
#3770000
0(
#3775000
b1001 D
1(
#3780000
0(
#3785000
b1010 D
1(
#3790000
0(
#3795000
b1011 D
1(
#3800000
0(
#3805000
b1100 D
1(
#3810000
0(
#3815000
b1101 D
1(
#3820000
0(
#3825000
b1110 D
1(
#3830000
0(
#3835000
b1111 D
1(
#3840000
0(
#3845000
b10000 D
1(
#3850000
0(
#3855000
b10001 D
1(
#3860000
0(
#3865000
b10010 D
1(
#3870000
0(
#3875000
b10011 D
1(
#3880000
0(
#3885000
b10100 D
1(
#3890000
0(
#3895000
b1101 C
b0 D
1(
#3900000
0(
#3905000
b1 D
0%
0E
1(
#3910000
0(
#3915000
b10 D
1(
#3920000
0(
#3925000
b11 D
1(
#3930000
0(
#3935000
b100 D
1(
#3940000
0(
#3945000
b101 D
1(
#3950000
0(
#3955000
b110 D
1(
#3960000
0(
#3965000
b111 D
1(
#3970000
0(
#3975000
b1000 D
1(
#3980000
0(
#3985000
b1001 D
1(
#3990000
0(
#3995000
b1010 D
1(
#4000000
0(
#4005000
b1011 D
1(
#4010000
0(
#4015000
b1100 D
1(
#4020000
0(
#4025000
b1101 D
1(
#4030000
0(
#4035000
b1110 D
1(
#4040000
0(
#4045000
b1111 D
1(
#4050000
0(
#4055000
b10000 D
1(
#4060000
0(
#4065000
b10001 D
1(
#4070000
0(
#4075000
b10010 D
1(
#4080000
0(
#4085000
b10011 D
1(
#4090000
0(
#4095000
b10100 D
1(
#4100000
0(
#4105000
b10101 D
1(
#4110000
0(
#4115000
b10110 D
1(
#4120000
0(
#4125000
b1010 C
b0 D
1(
#4130000
0(
#4135000
b0 !
b0 0
1"
1K
0#
0J
b1110 C
1F
1(
#4140000
0(
#4145000
b1 D
1%
1E
b1 /
1,
1(
#4150000
0(
#4155000
b10 D
b10 /
1(
#4160000
0(
#4165000
b11 D
b11 /
1(
#4170000
0(
#4175000
b100 D
b0 +
1(
#4180000
0(
#4185000
b101 D
1(
#4190000
0(
#4195000
b110 D
1(
#4200000
0(
#4205000
b111 D
1(
#4210000
0(
#4215000
b1000 D
1(
#4220000
0(
#4225000
b1001 D
1(
#4230000
0(
#4235000
b1010 D
1(
#4240000
0(
#4245000
b1011 D
1(
#4250000
0(
