Projetos/Modulo LCD DE2 Cyclone II/LCD.v
module LCD (data, selectCD, clk, rst, LCD_DATA, LCD_RW, LCD_RS, LCD_ON, LCD_BLON, LCD_EN, enableWriting, LCD_Available);

    input wire [31:0] data;
    input wire selectCD;
    input wire enableWriting;
    input wire clk;
    input wire rst;

    inout wire [7:0] LCD_DATA;

    output wire LCD_RW;
    output wire LCD_RS;
    output wire LCD_ON;
    output wire LCD_BLON;
    output wire LCD_Available;
    output wire LCD_EN;

    wire LCD_BUSYFLAG;


    reg select_ReadOrWrite;
    reg enableNext;
    reg select_CommandOrData;
    reg powerON;
    reg backlightON;
    reg actualLine;
    reg LCDAvailable;
    reg [31:0] localData;
    reg hasTested;

    //Pin assignments

    assign LCD_DATA = (select_ReadOrWrite == 1'b0) ? currCmd : 8'bz;
    assign LCD_RW = select_ReadOrWrite;
    assign LCD_RS = select_CommandOrData;
    assign LCD_ON = powerON;
    assign LCD_BLON = backlightON;
    assign LCD_Available = LCDAvailable;
    assign LCD_BUSYFLAG = LCD_DATA[7];
    assign LCD_EN = enableNext;


    //For the FSA ---------------------------------------------------------------------

    reg [3:0] currState;
    reg [5:0] delayClocks;
    reg [7:0] currCmd;
    reg [3:0] nextState;

    parameter initState1 = 4'd0;
    parameter initStateCommand = 4'd1;
    parameter initState2 = 4'd2;
    parameter byte0 = 4'd4;
    parameter byte1 = 4'd5;
    parameter byte2 = 4'd6;
    parameter byte3 = 4'd7;
    parameter waitingState = 4'd8;
    parameter idle = 4'd9;
    parameter waitNotBusy = 4'd10;
    parameter PULSE_LOW = 4'd13;
    parameter PULSE_HIGH = 4'd14;
    parameter resetState = 4'd15;
    

    

    always @(posedge clk or posedge rst) begin
        if (rst) begin
            currState <= resetState;
            LCDAvailable <= 1'b0;
            enableNext <= 1'b0;
            hasTested <= 1'b0;
            delayClocks <= 0;
        end

        else begin
            case (currState)
                initState1: begin
                    currCmd <= 8'h0C;
                    select_CommandOrData <= 1'b0;
                    localData <= 32'b0;
                    currState <= PULSE_HIGH;
                    nextState <= waitingState;
                    LCDAvailable <= 1'b0;

                end

                initState2: begin
                    currCmd <= 8'h00;
                    select_CommandOrData <= 1'b0;
                    select_ReadOrWrite <= 1'b0;
                    localData <= data;
                    currState <= PULSE_HIGH;
                    nextState <= (selectCD) ? byte0 : initStateCommand;
                    LCDAvailable <= 1'b0;
                    


                end

                byte0: begin
                    select_ReadOrWrite <= 1'b0;
                    select_CommandOrData <= 1'b1;
                    currCmd <= localData[31:24];
                    
                    currState <= PULSE_HIGH;
                    nextState <= byte1;
                    

                end

                byte1: begin
                    select_ReadOrWrite <= 1'b0;
                    enableNext <= 1'b0;
                    select_CommandOrData <= 1'b1;
                    currCmd <= localData[23:16];
                    
                    currState <= PULSE_HIGH;
                    nextState <= byte2;

                end
                byte2: begin
                    
                    enableNext <= 1'b0;
                    select_CommandOrData <= 1'b1;
                    currCmd <= localData[15:8];
                    
                    currState <= PULSE_HIGH;
                    nextState <= byte3;

                end
                byte3: begin
                    select_ReadOrWrite <= 1'b0;
                    enableNext <= 1'b0;
                    select_CommandOrData <= 1'b1;
                    currCmd <= localData[7:0];
                    
                    currState <= PULSE_HIGH;
                    nextState <= waitingState;
                    

                end

                waitNotBusy: begin

                    if (hasTested) begin
                        hasTested <= 1'b0;
                        if (!LCD_BUSYFLAG) begin
                            currState <= nextState;
                            select_ReadOrWrite <= 1'b0;
                        end
                        else begin
                            currState <= waitNotBusy;
                        end
                    end
                    else begin
                        hasTested <= 1'b1;
                        currState <= PULSE_HIGH;
                        select_CommandOrData <= 1'b0;
                        select_ReadOrWrite <= 1'b1;
                    end

                end

                waitingState: begin
                    currCmd <= 8'h00;
                    LCDAvailable <= 1'b1;
                    select_CommandOrData <= 1'b0;
                    currState <= (enableWriting) ? initState2 : waitingState;
                    LCDAvailable <= 1'b1;
                end

                resetState: begin
                    enableNext <= 1'b0;
                    select_ReadOrWrite <= 1'b0;
                    select_CommandOrData <= 1'b0;
                    powerON <= 1'b1;
                    backlightON <= 1'b1;
                    currCmd <= 8'h38;
                    LCDAvailable <= 1'b0;
                    hasTested <= 1'b0;

                    currState <= PULSE_HIGH;
                    nextState <= initState1;

                end

                PULSE_HIGH: begin
                    
                    enableNext <= 1'b1;
                    if (delayClocks < 20) begin
                        delayClocks <= delayClocks + 1;
                        currState <= PULSE_HIGH;
                    end
                    else begin
                        delayClocks <= 0;
                        currState <= PULSE_LOW;
                    end

                end

                PULSE_LOW: begin
                    
                    enableNext <= 1'b0;
                    if (delayClocks < 22) begin
                        delayClocks <= delayClocks + 1;
                        currState <= PULSE_LOW;
                    end
                    else begin
                        delayClocks <= 0;
                        currState <= waitNotBusy;
                    end

                end

                default: begin
                    
                    currState <= resetState;

                end
            endcase

        end
    end

    //--------------------------------------------------------


endmodule

Projetos/Modulo LCD DE2 Cyclone II/LCD_testbench2.v
`timescale 1us/1ns

module LCD_testbench2;

  // Sinais de estímulo para o módulo LCD
  reg  [31:0] data;
  reg         selectCD;
  reg         enableWriting;
  reg         clk;
  reg         rst;

  // Sinais do fake driver para simular o comportamento interno do LCD
  reg  [7:0]  fake_LCD_data;
  reg         fake_driver_enable;
  integer     busy_counter;

  // Declaramos LCD_DATA como tri0 para que, quando não for dirigido pelo módulo,
  // ele assuma o valor default 0 (busy flag baixo)
  tri0 [7:0] LCD_DATA;

  wire LCD_RW;
  wire LCD_RS;
  wire LCD_ON;
  wire LCD_BLON;
  wire LCD_Available;
  // (Opcional) Se seu módulo LCD tiver um sinal de enable de LCD, pode ser conectado
  wire LCD_EN;

  // Instanciação do módulo LCD (Unidade Sob Teste)
  LCD uut (
    .data(data),
    .selectCD(selectCD),
    .clk(clk),
    .rst(rst),
    .LCD_DATA(LCD_DATA),
    .LCD_RW(LCD_RW),
    .LCD_RS(LCD_RS),
    .LCD_ON(LCD_ON),
    .LCD_BLON(LCD_BLON),
    .enableWriting(enableWriting),
    .LCD_Available(LCD_Available),
    .LCD_EN(LCD_EN)
  );

  // ---------------------------------------------------------------
  // Bloco Fake LCD: simula a resposta interna do HD44780U
  // Quando o módulo coloca LCD_DATA em tri-state (modo leitura) 
  // (ou seja, LCD_RW == 1), o fake driver injeta um valor com busy flag alto
  // durante 3 ciclos e depois libera (busy flag 0).
  // ---------------------------------------------------------------
  initial begin
    fake_LCD_data = 8'h80;  // busy flag alto (bit7 = 1)
    fake_driver_enable = 0;
    busy_counter = 0;
  end

  always @(posedge clk) begin
    if (LCD_RW == 1'b1) begin
      // Ativa o driver fake quando o módulo está em modo leitura
      fake_driver_enable <= 1'b1;
      if (busy_counter < 3)
        busy_counter <= busy_counter + 1;
      else
        fake_LCD_data <= 8'h00;  // Após 3 ciclos, busy flag desativa
    end else begin
      fake_driver_enable <= 1'b0;
      busy_counter <= 0;
      fake_LCD_data <= 8'h80; // Prepara para nova simulação de busy
    end
  end

  // Se o módulo não estiver dirigindo o barramento, o fake driver assume.
  assign LCD_DATA = fake_driver_enable ? fake_LCD_data : 8'bz;

  // ---------------------------------------------------------------
  // Gerador de clock: período de 10 us
  // ---------------------------------------------------------------
  initial begin
    clk = 0;
    forever #5 clk = ~clk;  // #5 equivale a 5 us, totalizando 10 us de período
  end

  // ---------------------------------------------------------------
  // Máquina de Estados do Testbench para sequenciar os estímulos
  // ---------------------------------------------------------------
  // Definindo os estados:
  localparam INIT             = 0;
  localparam WAIT_AVAIL       = 1;
  localparam SEND_FIRST       = 2;
  localparam WAIT_FIRST_DONE  = 3;
  localparam SEND_SECOND      = 4;
  localparam WAIT_SECOND_DONE = 5;
  localparam SEND_THIRD       = 6;
  localparam WAIT_THIRD_DONE  = 7;
  localparam FINISH           = 8;

  reg [3:0] test_state;
  reg [15:0] delay_counter;  // Contador para gerar atrasos se necessário

  // Máquina de estados síncrona
  always @(posedge clk or posedge rst) begin
    if (rst) begin
      test_state    <= INIT;
      data          <= 32'b0;
      selectCD      <= 1;         // 1 indica escrita de dados
      enableWriting <= 0;
      delay_counter <= 0;
    end else begin
      case (test_state)
        INIT: begin
          // Aguarda alguns ciclos após o reset para estabilização
          if (delay_counter < 5) begin
            delay_counter <= delay_counter + 1;
            enableWriting <= 0;
          end else begin
            delay_counter <= 0;
            test_state <= WAIT_AVAIL;
          end
        end

        WAIT_AVAIL: begin
          // Aguarda LCD_Available ficar 1
          if (LCD_Available == 1)
            test_state <= SEND_FIRST;
        end

        SEND_FIRST: begin
          // Envia "HELL"
          data <= "HELL";  // Literal empacotado (MSB = 'H')
          enableWriting <= 1;
          test_state <= WAIT_FIRST_DONE;
        end

        WAIT_FIRST_DONE: begin
          // Desativa o enableWriting e aguarda LCD_Available
          enableWriting <= 0;
          if (LCD_Available == 1)
            test_state <= SEND_SECOND;
        end

        SEND_SECOND: begin
          // Envia "O WI"
          data <= "O WI";
          enableWriting <= 1;
          test_state <= WAIT_SECOND_DONE;
        end

        WAIT_SECOND_DONE: begin
          enableWriting <= 0;
          if (LCD_Available == 1)
            test_state <= SEND_THIRD;
        end

        SEND_THIRD: begin
          // Envia "LL! " (com espaço, se desejar)
          data <= "LL! ";
          enableWriting <= 1;
          test_state <= WAIT_THIRD_DONE;
        end

        WAIT_THIRD_DONE: begin
          enableWriting <= 0;
          if (LCD_Available == 1)
            test_state <= FINISH;
        end

        FINISH: begin
          // Aguarda alguns ciclos antes de terminar a simulação
          if (delay_counter < 10)
            delay_counter <= delay_counter + 1;
          else
            $finish;
        end

        default: test_state <= INIT;
      endcase
    end
  end

  // ---------------------------------------------------------------
  // Inicialização do reset (apenas para o testbench)
  // ---------------------------------------------------------------
  initial begin
    $dumpfile("LCD_testbench2.vcd");
    $dumpvars(0, LCD_testbench2);
    rst = 1;
    #20;
    rst = 0;
  end

endmodule

Projetos/Modulo LCD DE2 Cyclone II/LCD_testbench2.vcd
$date
	Tue Mar 18 22:01:35 2025
$end
$version
	Icarus Verilog
$end
$timescale
	1ns
$end
$scope module LCD_testbench2 $end
$var wire 8 ! LCD_DATA [7:0] $end
$var wire 1 " LCD_RW $end
$var wire 1 # LCD_RS $end
$var wire 1 $ LCD_ON $end
$var wire 1 % LCD_EN $end
$var wire 1 & LCD_BLON $end
$var wire 1 ' LCD_Available $end
$var parameter 32 ( FINISH $end
$var parameter 32 ) INIT $end
$var parameter 32 * SEND_FIRST $end
$var parameter 32 + SEND_SECOND $end
$var parameter 32 , SEND_THIRD $end
$var parameter 32 - WAIT_AVAIL $end
$var parameter 32 . WAIT_FIRST_DONE $end
$var parameter 32 / WAIT_SECOND_DONE $end
$var parameter 32 0 WAIT_THIRD_DONE $end
$var reg 1 1 clk $end
$var reg 32 2 data [31:0] $end
$var reg 16 3 delay_counter [15:0] $end
$var reg 1 4 enableWriting $end
$var reg 8 5 fake_LCD_data [7:0] $end
$var reg 1 6 fake_driver_enable $end
$var reg 1 7 rst $end
$var reg 1 8 selectCD $end
$var reg 4 9 test_state [3:0] $end
$var integer 32 : busy_counter [31:0] $end
$scope module uut $end
$var wire 1 ' LCD_Available $end
$var wire 1 & LCD_BLON $end
$var wire 8 ; LCD_DATA [7:0] $end
$var wire 1 % LCD_EN $end
$var wire 1 $ LCD_ON $end
$var wire 1 # LCD_RS $end
$var wire 1 " LCD_RW $end
$var wire 1 1 clk $end
$var wire 32 < data [31:0] $end
$var wire 1 4 enableWriting $end
$var wire 1 7 rst $end
$var wire 1 8 selectCD $end
$var wire 1 = LCD_BUSYFLAG $end
$var parameter 4 > PULSE_HIGH $end
$var parameter 4 ? PULSE_LOW $end
$var parameter 4 @ byte0 $end
$var parameter 4 A byte1 $end
$var parameter 4 B byte2 $end
$var parameter 4 C byte3 $end
$var parameter 4 D idle $end
$var parameter 4 E initState1 $end
$var parameter 4 F initState2 $end
$var parameter 4 G initStateCommand $end
$var parameter 4 H resetState $end
$var parameter 4 I waitNotBusy $end
$var parameter 4 J waitingState $end
$var reg 1 K LCDAvailable $end
$var reg 1 L backlightON $end
$var reg 8 M currCmd [7:0] $end
$var reg 4 N currState [3:0] $end
$var reg 6 O delayClocks [5:0] $end
$var reg 1 P enableNext $end
$var reg 1 Q hasTested $end
$var reg 32 R localData [31:0] $end
$var reg 4 S nextState [3:0] $end
$var reg 1 T powerON $end
$var reg 1 U select_CommandOrData $end
$var reg 1 V select_ReadOrWrite $end
$upscope $end
$upscope $end
$enddefinitions $end
$comment Show the parameter values. $end
$dumpall
b1000 J
b1010 I
b1111 H
b1 G
b10 F
b0 E
b1001 D
b111 C
b110 B
b101 A
b100 @
b1101 ?
b1110 >
b111 0
b101 /
b11 .
b1 -
b110 ,
b100 +
b10 *
b0 )
b1000 (
$end
#0
$dumpvars
xV
xU
xT
bx S
bx R
0Q
0P
b0 O
b1111 N
bx M
xL
0K
x=
b0 <
bx ;
b0 :
b0 9
18
17
06
b10000000 5
04
b0 3
b0 2
01
0'
x&
0%
x$
x#
x"
bx !
$end
#5000
11
#10000
01
#15000
11
#20000
01
07
#25000
0=
b111000 !
b111000 ;
b1 3
b0 S
b1110 N
b111000 M
1&
1L
1$
1T
0#
0U
0"
0V
11
#30000
01
#35000
b1 O
1%
1P
b10 3
11
#40000
01
#45000
b11 3
b10 O
11
#50000
01
#55000
b11 O
b100 3
11
#60000
01
#65000
b101 3
b100 O
11
#70000
01
#75000
b101 O
b1 9
b0 3
11
#80000
01
#85000
b110 O
11
#90000
01
#95000
b111 O
11
#100000
01
#105000
b1000 O
11
#110000
01
#115000
b1001 O
11
#120000
01
#125000
b1010 O
11
#130000
01
#135000
b1011 O
11
#140000
01
#145000
b1100 O
11
#150000
01
#155000
b1101 O
11
#160000
01
#165000
b1110 O
11
#170000
01
#175000
b1111 O
11
#180000
01
#185000
b10000 O
11
#190000
01
#195000
b10001 O
11
#200000
01
#205000
b10010 O
11
#210000
01
#215000
b10011 O
11
#220000
01
#225000
b10100 O
11
#230000
01
#235000
b1101 N
b0 O
11
#240000
01
#245000
b1 O
0%
0P
11
#250000
01
#255000
b10 O
11
#260000
01
#265000
b11 O
11
#270000
01
#275000
b100 O
11
#280000
01
#285000
b101 O
11
#290000
01
#295000
b110 O
11
#300000
01
#305000
b111 O
11
#310000
01
#315000
b1000 O
11
#320000
01
#325000
b1001 O
11
#330000
01
#335000
b1010 O
11
#340000
01
#345000
b1011 O
11
#350000
01
#355000
b1100 O
11
#360000
01
#365000
b1101 O
11
#370000
01
#375000
b1110 O
11
#380000
01
#385000
b1111 O
11
#390000
01
#395000
b10000 O
11
#400000
01
#405000
b10001 O
11
#410000
01
#415000
b10010 O
11
#420000
01
#425000
b10011 O
11
#430000
01
#435000
b10100 O
11
#440000
01
#445000
b10101 O
11
#450000
01
#455000
b10110 O
11
#460000
01
#465000
b1010 N
b0 O
11
#470000
01
#475000
b0 !
b0 ;
1"
1V
b1110 N
1Q
11
#480000
01
#485000
1=
b10000000 !
b10000000 ;
b1 O
1%
1P
b1 :
16
11
#490000
01
#495000
b10 O
b10 :
11
#500000
01
#505000
b11 O
b11 :
11
#510000
01
#515000
0=
b0 !
b0 ;
b100 O
b0 5
11
#520000
01
#525000
b101 O
11
#530000
01
#535000
b110 O
11
#540000
01
#545000
b111 O
11
#550000
01
#555000
b1000 O
11
#560000
01
#565000
b1001 O
11
#570000
01
#575000
b1010 O
11
#580000
01
#585000
b1011 O
11
#590000
01
#595000
b1100 O
11
#600000
01
#605000
b1101 O
11
#610000
01
#615000
b1110 O
11
#620000
01
#625000
b1111 O
11
#630000
01
#635000
b10000 O
11
#640000
01
#645000
b10001 O
11
#650000
01
#655000
b10010 O
11
#660000
01
#665000
b10011 O
11
#670000
01
#675000
b10100 O
11
#680000
01
#685000
b1101 N
b0 O
11
#690000
01
#695000
b1 O
0%
0P
11
#700000
01
#705000
b10 O
11
#710000
01
#715000
b11 O
11
#720000
01
#725000
b100 O
11
#730000
01
#735000
b101 O
11
#740000
01
#745000
b110 O
11
#750000
01
#755000
b111 O
11
#760000
01
#765000
b1000 O
11
#770000
01
#775000
b1001 O
11
#780000
01
#785000
b1010 O
11
#790000
01
#795000
b1011 O
11
#800000
01
#805000
b1100 O
11
#810000
01
#815000
b1101 O
11
#820000
01
#825000
b1110 O
11
#830000
01
#835000
b1111 O
11
#840000
01
#845000
b10000 O
11
#850000
01
#855000
b10001 O
11
#860000
01
#865000
b10010 O
11
#870000
01
#875000
b10011 O
11
#880000
01
#885000
b10100 O
11
#890000
01
#895000
b10101 O
11
#900000
01
#905000
b10110 O
11
#910000
01
#915000
b1010 N
b0 O
11
#920000
01
#925000
b0xxx000 !
b0xxx000 ;
0"
0V
b0 N
0Q
11
#930000
01
#935000
b1100 !
b1100 ;
b1000 S
b1110 N
b0 R
b1100 M
b10000000 5
b0 :
06
11
#940000
01
#945000
b1 O
1%
1P
11
#950000
01
#955000
b10 O
11
#960000
01
#965000
b11 O
11
#970000
01
#975000
b100 O
11
#980000
01
#985000
b101 O
11
#990000
01
#995000
b110 O
11
#1000000
01
#1005000
b111 O
11
#1010000
01
#1015000
b1000 O
11
#1020000
01
#1025000
b1001 O
11
#1030000
01
#1035000
b1010 O
11
#1040000
01
#1045000
b1011 O
11
#1050000
01
#1055000
b1100 O
11
#1060000
01
#1065000
b1101 O
11
#1070000
01
#1075000
b1110 O
11
#1080000
01
#1085000
b1111 O
11
#1090000
01
#1095000
b10000 O
11
#1100000
01
#1105000
b10001 O
11
#1110000
01
#1115000
b10010 O
11
#1120000
01
#1125000
b10011 O
11
#1130000
01
#1135000
b10100 O
11
#1140000
01
#1145000
b1101 N
b0 O
11
#1150000
01
#1155000
b1 O
0%
0P
11
#1160000
01
#1165000
b10 O
11
#1170000
01
#1175000
b11 O
11
#1180000
01
#1185000
b100 O
11
#1190000
01
#1195000
b101 O
11
#1200000
01
#1205000
b110 O
11
#1210000
01
#1215000
b111 O
11
#1220000
01
#1225000
b1000 O
11
#1230000
01
#1235000
b1001 O
11
#1240000
01
#1245000
b1010 O
11
#1250000
01
#1255000
b1011 O
11
#1260000
01
#1265000
b1100 O
11
#1270000
01
#1275000
b1101 O
11
#1280000
01
#1285000
b1110 O
11
#1290000
01
#1295000
b1111 O
11
#1300000
01
#1305000
b10000 O
11
#1310000
01
#1315000
b10001 O
11
#1320000
01
#1325000
b10010 O
11
#1330000
01
#1335000
b10011 O
11
#1340000
01
#1345000
b10100 O
11
#1350000
01
#1355000
b10101 O
11
#1360000
01
#1365000
b10110 O
11
#1370000
01
#1375000
b1010 N
b0 O
11
#1380000
01
#1385000
b0 !
b0 ;
1"
1V
b1110 N
1Q
11
#1390000
01
#1395000
1=
b10000000 !
b10000000 ;
b1 O
1%
1P
b1 :
16
11
#1400000
01
#1405000
b10 O
b10 :
11
#1410000
01
#1415000
b11 O
b11 :
11
#1420000
01
#1425000
0=
b0 !
b0 ;
b100 O
b0 5
11
#1430000
01
#1435000
b101 O
11
#1440000
01
#1445000
b110 O
11
#1450000
01
#1455000
b111 O
11
#1460000
01
#1465000
b1000 O
11
#1470000
01
#1475000
b1001 O
11
#1480000
01
#1485000
b1010 O
11
#1490000
01
#1495000
b1011 O
11
#1500000
01
#1505000
b1100 O
11
#1510000
01
#1515000
b1101 O
11
#1520000
01
#1525000
b1110 O
11
#1530000
01
#1535000
b1111 O
11
#1540000
01
#1545000
b10000 O
11
#1550000
01
#1555000
b10001 O
11
#1560000
01
#1565000
b10010 O
11
#1570000
01
#1575000
b10011 O
11
#1580000
01
#1585000
b10100 O
11
#1590000
01
#1595000
b1101 N
b0 O
11
#1600000
01
#1605000
b1 O
0%
0P
11
#1610000
01
#1615000
b10 O
11
#1620000
01
#1625000
b11 O
11
#1630000
01
#1635000
b100 O
11
#1640000
01
#1645000
b101 O
11
#1650000
01
#1655000
b110 O
11
#1660000
01
#1665000
b111 O
11
#1670000
01
#1675000
b1000 O
11
#1680000
01
#1685000
b1001 O
11
#1690000
01
#1695000
b1010 O
11
#1700000
01
#1705000
b1011 O
11
#1710000
01
#1715000
b1100 O
11
#1720000
01
#1725000
b1101 O
11
#1730000
01
#1735000
b1110 O
11
#1740000
01
#1745000
b1111 O
11
#1750000
01
#1755000
b10000 O
11
#1760000
01
#1765000
b10001 O
11
#1770000
01
#1775000
b10010 O
11
#1780000
01
#1785000
b10011 O
11
#1790000
01
#1795000
b10100 O
11
#1800000
01
#1805000
b10101 O
11
#1810000
01
#1815000
b10110 O
11
#1820000
01
#1825000
b1010 N
b0 O
11
#1830000
01
#1835000
b0xx00 !
b0xx00 ;
0"
0V
b1000 N
0Q
11
#1840000
01
#1845000
b0 !
b0 ;
1'
1K
b0 M
b10000000 5
b0 :
06
11
#1850000
01
#1855000
b10 9
11
#1860000
01
#1865000
b11 9
14
b1001000010001010100110001001100 2
b1001000010001010100110001001100 <
11
#1870000
01
#1875000
b10 N
b100 9
04
11
#1880000
01
#1885000
b101 9
14
b1001111001000000101011101001001 2
b1001111001000000101011101001001 <
0'
0K
b100 S
b1110 N
b1001000010001010100110001001100 R
11
#1890000
01
#1895000
b1 O
1%
1P
04
11
#1900000
01
#1905000
b10 O
11
#1910000
01
#1915000
b11 O
11
#1920000
01
#1925000
b100 O
11
#1930000
01
#1935000
b101 O
11
#1940000
01
#1945000
b110 O
11
#1950000
01
#1955000
b111 O
11
#1960000
01
#1965000
b1000 O
11
#1970000
01
#1975000
b1001 O
11
#1980000
01
#1985000
b1010 O
11
#1990000
01
#1995000
b1011 O
11
#2000000
01
#2005000
b1100 O
11
#2010000
01
#2015000
b1101 O
11
#2020000
01
#2025000
b1110 O
11
#2030000
01
#2035000
b1111 O
11
#2040000
01
#2045000
b10000 O
11
#2050000
01
#2055000
b10001 O
11
#2060000
01
#2065000
b10010 O
11
#2070000
01
#2075000
b10011 O
11
#2080000
01
#2085000
b10100 O
11
#2090000
01
#2095000
b1101 N
b0 O
11
#2100000
01
#2105000
b1 O
0%
0P
11
#2110000
01
#2115000
b10 O
11
#2120000
01
#2125000
b11 O
11
#2130000
01
#2135000
b100 O
11
#2140000
01
#2145000
b101 O
11
#2150000
01
#2155000
b110 O
11
#2160000
01
#2165000
b111 O
11
#2170000
01
#2175000
b1000 O
11
#2180000
01
#2185000
b1001 O
11
#2190000
01
#2195000
b1010 O
11
#2200000
01
#2205000
b1011 O
11
#2210000
01
#2215000
b1100 O
11
#2220000
01
#2225000
b1101 O
11
#2230000
01
#2235000
b1110 O
11
#2240000
01
#2245000
b1111 O
11
#2250000
01
#2255000
b10000 O
11
#2260000
01
#2265000
b10001 O
11
#2270000
01
#2275000
b10010 O
11
#2280000
01
#2285000
b10011 O
11
#2290000
01
#2295000
b10100 O
11
#2300000
01
#2305000
b10101 O
11
#2310000
01
#2315000
b10110 O
11
#2320000
01
#2325000
b1010 N
b0 O
11
#2330000
01
#2335000
b0 !
b0 ;
1"
1V
b1110 N
1Q
11
#2340000
01
#2345000
1=
b10000000 !
b10000000 ;
b1 O
1%
1P
b1 :
16
11
#2350000
01
#2355000
b10 O
b10 :
11
#2360000
01
#2365000
b11 O
b11 :
11
#2370000
01
#2375000
0=
b0 !
b0 ;
b100 O
b0 5
11
#2380000
01
#2385000
b101 O
11
#2390000
01
#2395000
b110 O
11
#2400000
01
#2405000
b111 O
11
#2410000
01
#2415000
b1000 O
11
#2420000
01
#2425000
b1001 O
11
#2430000
01
#2435000
b1010 O
11
#2440000
01
#2445000
b1011 O
11
#2450000
01
#2455000
b1100 O
11
#2460000
01
#2465000
b1101 O
11
#2470000
01
#2475000
b1110 O
11
#2480000
01
#2485000
b1111 O
11
#2490000
01
#2495000
b10000 O
11
#2500000
01
#2505000
b10001 O
11
#2510000
01
#2515000
b10010 O
11
#2520000
01
#2525000
b10011 O
11
#2530000
01
#2535000
b10100 O
11
#2540000
01
#2545000
b1101 N
b0 O
11
#2550000
01
#2555000
b1 O
0%
0P
11
#2560000
01
#2565000
b10 O
11
#2570000
01
#2575000
b11 O
11
#2580000
01
#2585000
b100 O
11
#2590000
01
#2595000
b101 O
11
#2600000
01
#2605000
b110 O
11
#2610000
01
#2615000
b111 O
11
#2620000
01
#2625000
b1000 O
11
#2630000
01
#2635000
b1001 O
11
#2640000
01
#2645000
b1010 O
11
#2650000
01
#2655000
b1011 O
11
#2660000
01
#2665000
b1100 O
11
#2670000
01
#2675000
b1101 O
11
#2680000
01
#2685000
b1110 O
11
#2690000
01
#2695000
b1111 O
11
#2700000
01
#2705000
b10000 O
11
#2710000
01
#2715000
b10001 O
11
#2720000
01
#2725000
b10010 O
11
#2730000
01
#2735000
b10011 O
11
#2740000
01
#2745000
b10100 O
11
#2750000
01
#2755000
b10101 O
11
#2760000
01
#2765000
b10110 O
11
#2770000
01
#2775000
b1010 N
b0 O
11
#2780000
01
#2785000
0"
0V
b100 N
0Q
11
#2790000
01
#2795000
b1001000 !
b1001000 ;
b101 S
b1110 N
b1001000 M
1#
1U
b10000000 5
b0 :
06
11
#2800000
01
#2805000
b1 O
1%
1P
11
#2810000
01
#2815000
b10 O
11
#2820000
01
#2825000
b11 O
11
#2830000
01
#2835000
b100 O
11
#2840000
01
#2845000
b101 O
11
#2850000
01
#2855000
b110 O
11
#2860000
01
#2865000
b111 O
11
#2870000
01
#2875000
b1000 O
11
#2880000
01
#2885000
b1001 O
11
#2890000
01
#2895000
b1010 O
11
#2900000
01
#2905000
b1011 O
11
#2910000
01
#2915000
b1100 O
11
#2920000
01
#2925000
b1101 O
11
#2930000
01
#2935000
b1110 O
11
#2940000
01
#2945000
b1111 O
11
#2950000
01
#2955000
b10000 O
11
#2960000
01
#2965000
b10001 O
11
#2970000
01
#2975000
b10010 O
11
#2980000
01
#2985000
b10011 O
11
#2990000
01
#2995000
b10100 O
11
#3000000
01
#3005000
b1101 N
b0 O
11
#3010000
01
#3015000
b1 O
0%
0P
11
#3020000
01
#3025000
b10 O
11
#3030000
01
#3035000
b11 O
11
#3040000
01
#3045000
b100 O
11
#3050000
01
#3055000
b101 O
11
#3060000
01
#3065000
b110 O
11
#3070000
01
#3075000
b111 O
11
#3080000
01
#3085000
b1000 O
11
#3090000
01
#3095000
b1001 O
11
#3100000
01
#3105000
b1010 O
11
#3110000
01
#3115000
b1011 O
11
#3120000
01
#3125000
b1100 O
11
#3130000
01
#3135000
b1101 O
11
#3140000
01
#3145000
b1110 O
11
#3150000
01
#3155000
b1111 O
11
#3160000
01
#3165000
b10000 O
11
#3170000
01
#3175000
b10001 O
11
#3180000
01
#3185000
b10010 O
11
#3190000
01
#3195000
b10011 O
11
#3200000
01
#3205000
b10100 O
11
#3210000
01
#3215000
b10101 O
11
#3220000
01
#3225000
b10110 O
11
#3230000
01
#3235000
b1010 N
b0 O
11
#3240000
01
#3245000
b0 !
b0 ;
1"
1V
0#
0U
b1110 N
1Q
11
#3250000
01
#3255000
1=
b10000000 !
b10000000 ;
b1 O
1%
1P
b1 :
16
11
#3260000
01
#3265000
b10 O
b10 :
11
#3270000
01
#3275000
b11 O
b11 :
11
#3280000
01
#3285000
0=
b0 !
b0 ;
b100 O
b0 5
11
#3290000
01
#3295000
b101 O
11
#3300000
01
#3305000
b110 O
11
#3310000
01
#3315000
b111 O
11
#3320000
01
#3325000
b1000 O
11
#3330000
01
#3335000
b1001 O
11
#3340000
01
#3345000
b1010 O
11
#3350000
01
#3355000
b1011 O
11
#3360000
01
#3365000
b1100 O
11
#3370000
01
#3375000
b1101 O
11
#3380000
01
#3385000
b1110 O
11
#3390000
01
#3395000
b1111 O
11
#3400000
01
#3405000
b10000 O
11
#3410000
01
#3415000
b10001 O
11
#3420000
01
#3425000
b10010 O
11
#3430000
01
#3435000
b10011 O
11
#3440000
01
#3445000
b10100 O
11
#3450000
01
#3455000
b1101 N
b0 O
11
#3460000
01
#3465000
b1 O
0%
0P
11
#3470000
01
#3475000
b10 O
11
#3480000
01
#3485000
b11 O
11
#3490000
01
#3495000
b100 O
11
#3500000
01
#3505000
b101 O
11
#3510000
01
#3515000
b110 O
11
#3520000
01
#3525000
b111 O
11
#3530000
01
#3535000
b1000 O
11
#3540000
01
#3545000
b1001 O
11
#3550000
01
#3555000
b1010 O
11
#3560000
01
#3565000
b1011 O
11
#3570000
01
#3575000
b1100 O
11
#3580000
01
#3585000
b1101 O
11
#3590000
01
#3595000
b1110 O
11
#3600000
01
#3605000
b1111 O
11
#3610000
01
#3615000
b10000 O
11
#3620000
01
#3625000
b10001 O
11
#3630000
01
#3635000
b10010 O
11
#3640000
01
#3645000
b10011 O
11
#3650000
01
#3655000
b10100 O
11
#3660000
01
#3665000
b10101 O
11
#3670000
01
#3675000
b10110 O
11
#3680000
01
#3685000
b1010 N
b0 O
11
#3690000
01
#3695000
b0x00x000 !
b0x00x000 ;
0"
0V
b101 N
0Q
11
#3700000
01
#3705000
b1000101 !
b1000101 ;
b110 S
b1110 N
b1000101 M
1#
1U
b10000000 5
b0 :
06
11
#3710000
01
#3715000
b1 O
1%
1P
11
#3720000
01
#3725000
b10 O
11
#3730000
01
#3735000
b11 O
11
#3740000
01
#3745000
b100 O
11
#3750000
01
#3755000
b101 O
11
#3760000
01
#3765000
b110 O
11
#3770000
01
#3775000
b111 O
11
#3780000
01
#3785000
b1000 O
11
#3790000
01
#3795000
b1001 O
11
#3800000
01
#3805000
b1010 O
11
#3810000
01
#3815000
b1011 O
11
#3820000
01
#3825000
b1100 O
11
#3830000
01
#3835000
b1101 O
11
#3840000
01
#3845000
b1110 O
11
#3850000
01
#3855000
b1111 O
11
#3860000
01
#3865000
b10000 O
11
#3870000
01
#3875000
b10001 O
11
#3880000
01
#3885000
b10010 O
11
#3890000
01
#3895000
b10011 O
11
#3900000
01
#3905000
b10100 O
11
#3910000
01
#3915000
b1101 N
b0 O
11
#3920000
01
#3925000
b1 O
0%
0P
11
#3930000
01
#3935000
b10 O
11
#3940000
01
