Praticas/pratica01/somador4bits.v
/*
    * somador4bits.v
    *
    *  Created on: 1 de december de 2024

    Implemente um módulo somador de 4 bits em Verilog, implemente seu testbench, e
    ealize a simulação usando Icarus Verilog e Gtkwave para visualizar as formas de onda.



*/


//Módudo somador de 4 bits

module somador4bits (num1, num2, resultado);

    //Indicando os tipos das portas e os tamanhos:
    input wire [3:0] num1, num2; //Dois números de entrada de no máximo 4 bits
    output wire [4:0] resultado; //Saída de 4+1 bits

    //-------------------------------------------------------------------
    //Comportamento do circuito:

    assign resultado = num1 + num2; //Associa a saída do somador com a soma dos dois números de entrada


endmodule

Praticas/pratica01/somador4bits_tb.v
/*
    * somador4bits_tb.v
    *
    *  Created on: 1 de december de 2024

    Testbench para o somador4bits.v

    1) Realize a simulação exaustiva (todos as combinações de valores de A e B). Quanto
    tempo levou a simulação?
    2) Realize a simulação randomizada. Como garantir que a implementação está correta?
    
*/

`timescale 1ns / 100ps // DEFINE A UNIDADE DE TEMPO


module somador4bits_tb;

    reg [3:0] A, B;
    wire [4:0] Y;

    //INSTÂNCIA DO DUT (DESIGN UNDER TEST)

    somador4bits somador (.num1(A), .num2(B), .resultado(Y));


    //--------------------------------------------------------
    //BLOCO DE TESTES ------------

    initial begin
        $dumpfile("waveform_somador4bit.vcd"); //Criação do arquivo para o GTKWave
        $dumpvars(0, somador4bits_tb);


        $monitor("Time=%0d: a=%b b=%b y=%b", $time, A, B, Y); //Monitora automaticamente mudanças em variáveis.


        //SEÇÃO DE ESTÍMULOS -------
        
        $display("Testbench started");
        //Gerando todas as combinações possíveis
        for (integer i = 0; i < 16; i = i + 1) begin
            A = i[3:0];
            for (integer j = 0; j < 16; j = j + 1) begin
                B = j[3:0];
                #100; //Gera um atraso de 10 unidades
            end
        end

    end

endmodule

Praticas/pratica01/waveform_somador4bit.vcd
$date
	Sun Dec 01 13:13:01 2024
$end
$version
	Icarus Verilog
$end
$timescale
	100ps
$end
$scope module somador4bits_tb $end
$var wire 5 ! Y [4:0] $end
$var reg 4 " A [3:0] $end
$var reg 4 # B [3:0] $end
$scope module somador $end
$var wire 4 $ num1 [3:0] $end
$var wire 4 % num2 [3:0] $end
$var wire 5 & resultado [4:0] $end
$upscope $end
$scope begin $ivl_for_loop0 $end
$var integer 32 ' i [31:0] $end
$scope begin $ivl_for_loop1 $end
$var integer 32 ( j [31:0] $end
$upscope $end
$upscope $end
$upscope $end
$enddefinitions $end
$comment Show the parameter values. $end
$dumpall
$end
#0
$dumpvars
b0 (
b0 '
b0 &
b0 %
b0 $
b0 #
b0 "
b0 !
$end
#1000
b1 !
b1 &
b1 #
b1 %
b1 (
#2000
b10 !
b10 &
b10 #
b10 %
b10 (
#3000
b11 !
b11 &
b11 #
b11 %
b11 (
#4000
b100 !
b100 &
b100 #
b100 %
b100 (
#5000
b101 !
b101 &
b101 #
b101 %
b101 (
#6000
b110 !
b110 &
b110 #
b110 %
b110 (
#7000
b111 !
b111 &
b111 #
b111 %
b111 (
#8000
b1000 !
b1000 &
b1000 #
b1000 %
b1000 (
#9000
b1001 !
b1001 &
b1001 #
b1001 %
b1001 (
#10000
b1010 !
b1010 &
b1010 #
b1010 %
b1010 (
#11000
b1011 !
b1011 &
b1011 #
b1011 %
b1011 (
#12000
b1100 !
b1100 &
b1100 #
b1100 %
b1100 (
#13000
b1101 !
b1101 &
b1101 #
b1101 %
b1101 (
#14000
b1110 !
b1110 &
b1110 #
b1110 %
b1110 (
#15000
b1111 !
b1111 &
b1111 #
b1111 %
b1111 (
#16000
b0 #
b0 %
b1 !
b1 &
b1 "
b1 $
b1 '
b0 (
#17000
b10 !
b10 &
b1 #
b1 %
b1 (
#18000
b11 !
b11 &
b10 #
b10 %
b10 (
#19000
b100 !
b100 &
b11 #
b11 %
b11 (
#20000
b101 !
b101 &
b100 #
b100 %
b100 (
#21000
b110 !
b110 &
b101 #
b101 %
b101 (
#22000
b111 !
b111 &
b110 #
b110 %
b110 (
#23000
b1000 !
b1000 &
b111 #
b111 %
b111 (
#24000
b1001 !
b1001 &
b1000 #
b1000 %
b1000 (
#25000
b1010 !
b1010 &
b1001 #
b1001 %
b1001 (
#26000
b1011 !
b1011 &
b1010 #
b1010 %
b1010 (
#27000
b1100 !
b1100 &
b1011 #
b1011 %
b1011 (
#28000
b1101 !
b1101 &
b1100 #
b1100 %
b1100 (
#29000
b1110 !
b1110 &
b1101 #
b1101 %
b1101 (
#30000
b1111 !
b1111 &
b1110 #
b1110 %
b1110 (
#31000
b10000 !
b10000 &
b1111 #
b1111 %
b1111 (
#32000
b0 #
b0 %
b10 !
b10 &
b10 "
b10 $
b10 '
b0 (
#33000
b11 !
b11 &
b1 #
b1 %
b1 (
#34000
b100 !
b100 &
b10 #
b10 %
b10 (
#35000
b101 !
b101 &
b11 #
b11 %
b11 (
#36000
b110 !
b110 &
b100 #
b100 %
b100 (
#37000
b111 !
b111 &
b101 #
b101 %
b101 (
#38000
b1000 !
b1000 &
b110 #
b110 %
b110 (
#39000
b1001 !
b1001 &
b111 #
b111 %
b111 (
#40000
b1010 !
b1010 &
b1000 #
b1000 %
b1000 (
#41000
b1011 !
b1011 &
b1001 #
b1001 %
b1001 (
#42000
b1100 !
b1100 &
b1010 #
b1010 %
b1010 (
#43000
b1101 !
b1101 &
b1011 #
b1011 %
b1011 (
#44000
b1110 !
b1110 &
b1100 #
b1100 %
b1100 (
#45000
b1111 !
b1111 &
b1101 #
b1101 %
b1101 (
#46000
b10000 !
b10000 &
b1110 #
b1110 %
b1110 (
#47000
b10001 !
b10001 &
b1111 #
b1111 %
b1111 (
#48000
b0 #
b0 %
b11 !
b11 &
b11 "
b11 $
b11 '
b0 (
#49000
b100 !
b100 &
b1 #
b1 %
b1 (
#50000
b101 !
b101 &
b10 #
b10 %
b10 (
#51000
b110 !
b110 &
b11 #
b11 %
b11 (
#52000
b111 !
b111 &
b100 #
b100 %
b100 (
#53000
b1000 !
b1000 &
b101 #
b101 %
b101 (
#54000
b1001 !
b1001 &
b110 #
b110 %
b110 (
#55000
b1010 !
b1010 &
b111 #
b111 %
b111 (
#56000
b1011 !
b1011 &
b1000 #
b1000 %
b1000 (
#57000
b1100 !
b1100 &
b1001 #
b1001 %
b1001 (
#58000
b1101 !
b1101 &
b1010 #
b1010 %
b1010 (
#59000
b1110 !
b1110 &
b1011 #
b1011 %
b1011 (
#60000
b1111 !
b1111 &
b1100 #
b1100 %
b1100 (
#61000
b10000 !
b10000 &
b1101 #
b1101 %
b1101 (
#62000
b10001 !
b10001 &
b1110 #
b1110 %
b1110 (
#63000
b10010 !
b10010 &
b1111 #
b1111 %
b1111 (
#64000
b0 #
b0 %
b100 !
b100 &
b100 "
b100 $
b100 '
b0 (
#65000
b101 !
b101 &
b1 #
b1 %
b1 (
#66000
b110 !
b110 &
b10 #
b10 %
b10 (
#67000
b111 !
b111 &
b11 #
b11 %
b11 (
#68000
b1000 !
b1000 &
b100 #
b100 %
b100 (
#69000
b1001 !
b1001 &
b101 #
b101 %
b101 (
#70000
b1010 !
b1010 &
b110 #
b110 %
b110 (
#71000
b1011 !
b1011 &
b111 #
b111 %
b111 (
#72000
b1100 !
b1100 &
b1000 #
b1000 %
b1000 (
#73000
b1101 !
b1101 &
b1001 #
b1001 %
b1001 (
#74000
b1110 !
b1110 &
b1010 #
b1010 %
b1010 (
#75000
b1111 !
b1111 &
b1011 #
b1011 %
b1011 (
#76000
b10000 !
b10000 &
b1100 #
b1100 %
b1100 (
#77000
b10001 !
b10001 &
b1101 #
b1101 %
b1101 (
#78000
b10010 !
b10010 &
b1110 #
b1110 %
b1110 (
#79000
b10011 !
b10011 &
b1111 #
b1111 %
b1111 (
#80000
b0 #
b0 %
b101 !
b101 &
b101 "
b101 $
b101 '
b0 (
#81000
b110 !
b110 &
b1 #
b1 %
b1 (
#82000
b111 !
b111 &
b10 #
b10 %
b10 (
#83000
b1000 !
b1000 &
b11 #
b11 %
b11 (
#84000
b1001 !
b1001 &
b100 #
b100 %
b100 (
#85000
b1010 !
b1010 &
b101 #
b101 %
b101 (
#86000
b1011 !
b1011 &
b110 #
b110 %
b110 (
#87000
b1100 !
b1100 &
b111 #
b111 %
b111 (
#88000
b1101 !
b1101 &
b1000 #
b1000 %
b1000 (
#89000
b1110 !
b1110 &
b1001 #
b1001 %
b1001 (
#90000
b1111 !
b1111 &
b1010 #
b1010 %
b1010 (
#91000
b10000 !
b10000 &
b1011 #
b1011 %
b1011 (
#92000
b10001 !
b10001 &
b1100 #
b1100 %
b1100 (
#93000
b10010 !
b10010 &
b1101 #
b1101 %
b1101 (
#94000
b10011 !
b10011 &
b1110 #
b1110 %
b1110 (
#95000
b10100 !
b10100 &
b1111 #
b1111 %
b1111 (
#96000
b0 #
b0 %
b110 !
b110 &
b110 "
b110 $
b110 '
b0 (
#97000
b111 !
b111 &
b1 #
b1 %
b1 (
#98000
b1000 !
b1000 &
b10 #
b10 %
b10 (
#99000
b1001 !
b1001 &
b11 #
b11 %
b11 (
#100000
b1010 !
b1010 &
b100 #
b100 %
b100 (
#101000
b1011 !
b1011 &
b101 #
b101 %
b101 (
#102000
b1100 !
b1100 &
b110 #
b110 %
b110 (
#103000
b1101 !
b1101 &
b111 #
b111 %
b111 (
#104000
b1110 !
b1110 &
b1000 #
b1000 %
b1000 (
#105000
b1111 !
b1111 &
b1001 #
b1001 %
b1001 (
#106000
b10000 !
b10000 &
b1010 #
b1010 %
b1010 (
#107000
b10001 !
b10001 &
b1011 #
b1011 %
b1011 (
#108000
b10010 !
b10010 &
b1100 #
b1100 %
b1100 (
#109000
b10011 !
b10011 &
b1101 #
b1101 %
b1101 (
#110000
b10100 !
b10100 &
b1110 #
b1110 %
b1110 (
#111000
b10101 !
b10101 &
b1111 #
b1111 %
b1111 (
#112000
b0 #
b0 %
b111 !
b111 &
b111 "
b111 $
b111 '
b0 (
#113000
b1000 !
b1000 &
b1 #
b1 %
b1 (
#114000
b1001 !
b1001 &
b10 #
b10 %
b10 (
#115000
b1010 !
b1010 &
b11 #
b11 %
b11 (
#116000
b1011 !
b1011 &
b100 #
b100 %
b100 (
#117000
b1100 !
b1100 &
b101 #
b101 %
b101 (
#118000
b1101 !
b1101 &
b110 #
b110 %
b110 (
#119000
b1110 !
b1110 &
b111 #
b111 %
b111 (
#120000
b1111 !
b1111 &
b1000 #
b1000 %
b1000 (
#121000
b10000 !
b10000 &
b1001 #
b1001 %
b1001 (
#122000
b10001 !
b10001 &
b1010 #
b1010 %
b1010 (
#123000
b10010 !
b10010 &
b1011 #
b1011 %
b1011 (
#124000
b10011 !
b10011 &
b1100 #
b1100 %
b1100 (
#125000
b10100 !
b10100 &
b1101 #
b1101 %
b1101 (
#126000
b10101 !
b10101 &
b1110 #
b1110 %
b1110 (
#127000
b10110 !
b10110 &
b1111 #
b1111 %
b1111 (
#128000
b0 #
b0 %
b1000 !
b1000 &
b1000 "
b1000 $
b1000 '
b0 (
#129000
b1001 !
b1001 &
b1 #
b1 %
b1 (
#130000
b1010 !
b1010 &
b10 #
b10 %
b10 (
#131000
b1011 !
b1011 &
b11 #
b11 %
b11 (
#132000
b1100 !
b1100 &
b100 #
b100 %
b100 (
#133000
b1101 !
b1101 &
b101 #
b101 %
b101 (
#134000
b1110 !
b1110 &
b110 #
b110 %
b110 (
#135000
b1111 !
b1111 &
b111 #
b111 %
b111 (
#136000
b10000 !
b10000 &
b1000 #
b1000 %
b1000 (
#137000
b10001 !
b10001 &
b1001 #
b1001 %
b1001 (
#138000
b10010 !
b10010 &
b1010 #
b1010 %
b1010 (
#139000
b10011 !
b10011 &
b1011 #
b1011 %
b1011 (
#140000
b10100 !
b10100 &
b1100 #
b1100 %
b1100 (
#141000
b10101 !
b10101 &
b1101 #
b1101 %
b1101 (
#142000
b10110 !
b10110 &
b1110 #
b1110 %
b1110 (
#143000
b10111 !
b10111 &
b1111 #
b1111 %
b1111 (
#144000
b0 #
b0 %
b1001 !
b1001 &
b1001 "
b1001 $
b1001 '
b0 (
#145000
b1010 !
b1010 &
b1 #
b1 %
b1 (
#146000
b1011 !
b1011 &
b10 #
b10 %
b10 (
#147000
b1100 !
b1100 &
b11 #
b11 %
b11 (
#148000
b1101 !
b1101 &
b100 #
b100 %
b100 (
#149000
b1110 !
b1110 &
b101 #
b101 %
b101 (
#150000
b1111 !
b1111 &
b110 #
b110 %
b110 (
#151000
b10000 !
b10000 &
b111 #
b111 %
b111 (
#152000
b10001 !
b10001 &
b1000 #
b1000 %
b1000 (
#153000
b10010 !
b10010 &
b1001 #
b1001 %
b1001 (
#154000
b10011 !
b10011 &
b1010 #
b1010 %
b1010 (
#155000
b10100 !
b10100 &
b1011 #
b1011 %
b1011 (
#156000
b10101 !
b10101 &
b1100 #
b1100 %
b1100 (
#157000
b10110 !
b10110 &
b1101 #
b1101 %
b1101 (
#158000
b10111 !
b10111 &
b1110 #
b1110 %
b1110 (
#159000
b11000 !
b11000 &
b1111 #
b1111 %
b1111 (
#160000
b0 #
b0 %
b1010 !
b1010 &
b1010 "
b1010 $
b1010 '
b0 (
#161000
b1011 !
b1011 &
b1 #
b1 %
b1 (
#162000
b1100 !
b1100 &
b10 #
b10 %
b10 (
#163000
b1101 !
b1101 &
b11 #
b11 %
b11 (
#164000
b1110 !
b1110 &
b100 #
b100 %
b100 (
#165000
b1111 !
b1111 &
b101 #
b101 %
b101 (
#166000
b10000 !
b10000 &
b110 #
b110 %
b110 (
#167000
b10001 !
b10001 &
b111 #
b111 %
b111 (
#168000
b10010 !
b10010 &
b1000 #
b1000 %
b1000 (
#169000
b10011 !
b10011 &
b1001 #
b1001 %
b1001 (
#170000
b10100 !
b10100 &
b1010 #
b1010 %
b1010 (
#171000
b10101 !
b10101 &
b1011 #
b1011 %
b1011 (
#172000
b10110 !
b10110 &
b1100 #
b1100 %
b1100 (
#173000
b10111 !
b10111 &
b1101 #
b1101 %
b1101 (
#174000
b11000 !
b11000 &
b1110 #
b1110 %
b1110 (
#175000
b11001 !
b11001 &
b1111 #
b1111 %
b1111 (
#176000
b0 #
b0 %
b1011 !
b1011 &
b1011 "
b1011 $
b1011 '
b0 (
#177000
b1100 !
b1100 &
b1 #
b1 %
b1 (
#178000
b1101 !
b1101 &
b10 #
b10 %
b10 (
#179000
b1110 !
b1110 &
b11 #
b11 %
b11 (
#180000
b1111 !
b1111 &
b100 #
b100 %
b100 (
#181000
b10000 !
b10000 &
b101 #
b101 %
b101 (
#182000
b10001 !
b10001 &
b110 #
b110 %
b110 (
#183000
b10010 !
b10010 &
b111 #
b111 %
b111 (
#184000
b10011 !
b10011 &
b1000 #
b1000 %
b1000 (
#185000
b10100 !
b10100 &
b1001 #
b1001 %
b1001 (
#186000
b10101 !
b10101 &
b1010 #
b1010 %
b1010 (
#187000
b10110 !
b10110 &
b1011 #
b1011 %
b1011 (
#188000
b10111 !
b10111 &
b1100 #
b1100 %
b1100 (
#189000
b11000 !
b11000 &
b1101 #
b1101 %
b1101 (
#190000
b11001 !
b11001 &
b1110 #
b1110 %
b1110 (
#191000
b11010 !
b11010 &
b1111 #
b1111 %
b1111 (
#192000
b0 #
b0 %
b1100 !
b1100 &
b1100 "
b1100 $
b1100 '
b0 (
#193000
b1101 !
b1101 &
b1 #
b1 %
b1 (
#194000
b1110 !
b1110 &
b10 #
b10 %
b10 (
#195000
b1111 !
b1111 &
b11 #
b11 %
b11 (
#196000
b10000 !
b10000 &
b100 #
b100 %
b100 (
#197000
b10001 !
b10001 &
b101 #
b101 %
b101 (
#198000
b10010 !
b10010 &
b110 #
b110 %
b110 (
#199000
b10011 !
b10011 &
b111 #
b111 %
b111 (
#200000
b10100 !
b10100 &
b1000 #
b1000 %
b1000 (
#201000
b10101 !
b10101 &
b1001 #
b1001 %
b1001 (
#202000
b10110 !
b10110 &
b1010 #
b1010 %
b1010 (
#203000
b10111 !
b10111 &
b1011 #
b1011 %
b1011 (
#204000
b11000 !
b11000 &
b1100 #
b1100 %
b1100 (
#205000
b11001 !
b11001 &
b1101 #
b1101 %
b1101 (
#206000
b11010 !
b11010 &
b1110 #
b1110 %
b1110 (
#207000
b11011 !
b11011 &
b1111 #
b1111 %
b1111 (
#208000
b0 #
b0 %
b1101 !
b1101 &
b1101 "
b1101 $
b1101 '
b0 (
#209000
b1110 !
b1110 &
b1 #
b1 %
b1 (
#210000
b1111 !
b1111 &
b10 #
b10 %
b10 (
#211000
b10000 !
b10000 &
b11 #
b11 %
b11 (
#212000
b10001 !
b10001 &
b100 #
b100 %
b100 (
#213000
b10010 !
b10010 &
b101 #
b101 %
b101 (
#214000
b10011 !
b10011 &
b110 #
b110 %
b110 (
#215000
b10100 !
b10100 &
b111 #
b111 %
b111 (
#216000
b10101 !
b10101 &
b1000 #
b1000 %
b1000 (
#217000
b10110 !
b10110 &
b1001 #
b1001 %
b1001 (
#218000
b10111 !
b10111 &
b1010 #
b1010 %
b1010 (
#219000
b11000 !
b11000 &
b1011 #
b1011 %
b1011 (
#220000
b11001 !
b11001 &
b1100 #
b1100 %
b1100 (
#221000
b11010 !
b11010 &
b1101 #
b1101 %
b1101 (
#222000
b11011 !
b11011 &
b1110 #
b1110 %
b1110 (
#223000
b11100 !
b11100 &
b1111 #
b1111 %
b1111 (
#224000
b0 #
b0 %
b1110 !
b1110 &
b1110 "
b1110 $
b1110 '
b0 (
#225000
b1111 !
b1111 &
b1 #
b1 %
b1 (
#226000
b10000 !
b10000 &
b10 #
b10 %
b10 (
#227000
b10001 !
b10001 &
b11 #
b11 %
b11 (
#228000
b10010 !
b10010 &
b100 #
b100 %
b100 (
#229000
b10011 !
b10011 &
b101 #
b101 %
b101 (
#230000
b10100 !
b10100 &
b110 #
b110 %
b110 (
#231000
b10101 !
b10101 &
b111 #
b111 %
b111 (
#232000
b10110 !
b10110 &
b1000 #
b1000 %
b1000 (
#233000
b10111 !
b10111 &
b1001 #
b1001 %
b1001 (
#234000
b11000 !
b11000 &
b1010 #
b1010 %
b1010 (
#235000
b11001 !
b11001 &
b1011 #
b1011 %
b1011 (
#236000
b11010 !
b11010 &
b1100 #
b1100 %
b1100 (
#237000
b11011 !
b11011 &
b1101 #
b1101 %
b1101 (
#238000
b11100 !
b11100 &
b1110 #
b1110 %
b1110 (
#239000
b11101 !
b11101 &
b1111 #
b1111 %
b1111 (
#240000
b0 #
b0 %
b1111 !
b1111 &
b1111 "
b1111 $
b1111 '
b0 (
#241000
b10000 !
b10000 &
b1 #
b1 %
b1 (
#242000
b10001 !
b10001 &
b10 #
b10 %
b10 (
#243000
b10010 !
b10010 &
b11 #
b11 %
b11 (
#244000
b10011 !
b10011 &
b100 #
b100 %
b100 (
#245000
b10100 !
b10100 &
b101 #
b101 %
b101 (
#246000
b10101 !
b10101 &
b110 #
b110 %
b110 (
#247000
b10110 !
b10110 &
b111 #
b111 %
b111 (
#248000
b10111 !
b10111 &
b1000 #
b1000 %
b1000 (
#249000
b11000 !
b11000 &
b1001 #
b1001 %
b1001 (
#250000
b11001 !
b11001 &
b1010 #
b1010 %
b1010 (
#251000
b11010 !
b11010 &
b1011 #
b1011 %
b1011 (
#252000
b11011 !
b11011 &
b1100 #
b1100 %
b1100 (
#253000
b11100 !
b11100 &
b1101 #
b1101 %
b1101 (
#254000
b11101 !
b11101 &
b1110 #
b1110 %
b1110 (
#255000
b11110 !
b11110 &
b1111 #
b1111 %
b1111 (
#256000
b10000 '
b10000 (
