Praticas/pratica01/somador4bits.v
/*
    * somador4bits.v
    *
    *  Created on: 1 de december de 2024

    Implemente um módulo somador de 4 bits em Verilog, implemente seu testbench, e
    ealize a simulação usando Icarus Verilog e Gtkwave para visualizar as formas de onda.



*/


//Módudo somador de 4 bits

module somador4bits (num1, num2, resultado);

    //Indicando os tipos das portas e os tamanhos:
    input wire [3:0] num1, num2; //Dois números de entrada de no máximo 4 bits
    output wire [4:0] resultado; //Saída de 4+1 bits

    //-------------------------------------------------------------------
    //Comportamento do circuito:

    assign resultado = num1 + num2; //Associa a saída do somador com a soma dos dois números de entrada


endmodule

Praticas/pratica01/somador4bits_tbR.v
/*
    * somador4bits_tb.v
    *
    *  Created on: 1 de december de 2024

    Testbench para o somador4bits.v

    Funcionalidade de testes randomizados
    
*/

`timescale 1ns / 1ps // DEFINE A UNIDADE DE TEMPO


module somador4bits_tbR;

    reg [3:0] A, B;
    wire [4:0] Y;
    integer seed;
    integer somaObjetivo;

    //INSTÂNCIA DO DUT (DESIGN UNDER TEST)

    somador4bits somador (.num1(A), .num2(B), .resultado(Y));


    //--------------------------------------------------------
    //BLOCO DE TESTES ------------

    initial begin
        $dumpfile("waveform_somador4bitR.vcd"); //Criação do arquivo para o GTKWave
        $dumpvars(0, somador4bits_tbR);

        seed = 12430;
        somaObjetivo = 0;
        
        $monitor("Time=%0d: a=%b b=%b y=%b somaObjetivo=%b", $time, A, B, Y, somaObjetivo); //Monitora automaticamente mudanças em variáveis.


        //SEÇÃO DE ESTÍMULOS -------
        
        $display("Testbench comecou!");

        

        repeat (15) begin
            A = $urandom(seed);
            B = $urandom(seed);
            
            
            somaObjetivo = A + B;

            #10 //Para esperar o módulo do somador finalizar a soma

            if (somaObjetivo != Y) $display("Erro: somaObjetivo (%b) != Y (%b)", somaObjetivo[4:0], Y);

        end

        $finish
        

    end

endmodule

Praticas/pratica01/waveform_somador4bitR.vcd
$date
	Sun Dec 01 14:05:46 2024
$end
$version
	Icarus Verilog
$end
$timescale
	1ps
$end
$scope module somador4bits_tbR $end
$var wire 5 ! Y [4:0] $end
$var reg 4 " A [3:0] $end
$var reg 4 # B [3:0] $end
$var integer 32 $ seed [31:0] $end
$var integer 32 % somaObjetivo [31:0] $end
$scope module somador $end
$var wire 4 & num1 [3:0] $end
$var wire 4 ' num2 [3:0] $end
$var wire 5 ( resultado [4:0] $end
$upscope $end
$upscope $end
$enddefinitions $end
$comment Show the parameter values. $end
$dumpall
$end
#0
$dumpvars
b10100 (
b1110 '
b110 &
b10100 %
b1001111001110100100100010001100 $
b1110 #
b110 "
b10100 !
$end
#10000
b11010 %
b1011 #
b1011 '
b11010 !
b11010 (
b1111 "
b1111 &
b11001101111001110011010000111010 $
#20000
b1000 %
b0 #
b0 '
b1000 !
b1000 (
b1000 "
b1000 &
b11011000000010110010011100011000 $
#30000
b1110 %
b1100 #
b1100 '
b1110 !
b1110 (
b10 "
b10 &
b11001110000011110110000010100110 $
#40000
b101 %
b0 #
b0 '
b101 !
b101 (
b101 "
b101 &
b1111000000101000000110001100100 $
#50000
b1000 %
b110 #
b110 '
b1000 !
b1000 (
b10 "
b10 &
b10101011010011010010000111010010 $
#60000
b1100 %
b1100 !
b1100 (
b1010 #
b1010 '
b10010101001000100100010001110000 $
#70000
b10101 %
b1001 #
b1001 '
b10101 !
b10101 (
b1100 "
b1100 &
b1110100100010011010001110111110 $
#80000
b1111 %
b1111 !
b1111 (
b110 "
b110 &
b101100110101011101101100111100 $
#90000
b11000 %
b1011 #
b1011 '
b11000 !
b11000 (
b1101 "
b1101 &
b10101101111011101101001001101010 $
#100000
b1111 %
b1001 #
b1001 '
b1111 !
b1111 (
b110 "
b110 &
b11011100101011011001110011001000 $
#110000
b1110 %
b101 #
b101 '
b1110 !
b1110 (
b1001 "
b1001 &
b100010110100110101100111010110 $
#120000
b10 %
b1 #
b1 '
b10 !
b10 (
b1 "
b1 &
b1001000110100110001010100010100 $
#130000
b10100 %
b1000 #
b1000 '
b10100 !
b10100 (
b1100 "
b1100 &
b1100100011001101010011000000010 $
#140000
b10000 %
b1011 #
b1011 '
b10000 !
b10000 (
b101 "
b101 &
b10101101101001101001000000100000 $
